{"count": 1, "from": "<an118@vox.hacktic.nl> (Nobody)", "threads": [{"message_hash": "6999adf07affb0c48bec0a18441368d21b5fd92aec3299179dd2f58ada6a3981", "date": 776325974, "no_parent": null, "children": [{"message_hash": "39f63c85b48a4a6b985f61c541bbf445154351d4728f73b045448c607b7fc2ff", "date": 776347238, "no_parent": null, "children": [{"message_hash": "655c8cd70b35755c4450ad0141f43670a435e3b6cb1c8060408a925613c0f851", "date": 776383764, "no_parent": null, "children": [], "subject": "Re: amateur ciphers", "file_year": 1994, "from": "solman@MIT.EDU", "raw_date": "Mon, 8 Aug 94 15:09:24 PDT", "to": "perry@imsi.com", "reply_to": "<9408081200.AA21156@snark.imsi.com>", "message_id": "<9408082159.AA26505@ua.MIT.EDU>"}, {"message_hash": "62eae89f89ce40667affbfab4645bc25ed2537e9c8c3a353d0837f99c597f378", "date": 776410979, "no_parent": null, "children": [{"message_hash": "bf7ccf66bba047850ebbe930ae29dca8b7cf0eb09951a2a4025347e712ac93c2", "date": 776436965, "no_parent": null, "children": [], "subject": "Re: amateur ciphers", "file_year": 1994, "from": "\"Perry E. Metzger\" <perry@imsi.com>", "raw_date": "Tue, 9 Aug 94 05:56:05 PDT", "to": "Justin Lister <ruf@osiris.cs.uow.edu.au>", "reply_to": "<199408090541.AA14118@osiris.cs.uow.edu.au>", "message_id": "<9408091254.AA22930@snark.imsi.com>"}], "subject": "Re: amateur ciphers", "file_year": 1994, "from": "Justin Lister <ruf@osiris.cs.uow.edu.au>", "raw_date": "Mon, 8 Aug 94 22:42:59 PDT", "to": "cypherpunks@toad.com (Cypherpunk Mailing List)", "reply_to": "<9408081200.AA21156@snark.imsi.com>", "message_id": "<199408090541.AA14118@osiris.cs.uow.edu.au>"}], "subject": "amateur ciphers", "file_year": 1994, "from": "\"Perry E. Metzger\" <perry@imsi.com>", "raw_date": "Mon, 8 Aug 94 05:00:38 PDT", "to": "cypherpunks@toad.com", "reply_to": "<199408080606.AA26364@xs4all.hacktic.nl>", "message_id": "<9408081200.AA21156@snark.imsi.com>"}], "subject": "No Subject", "file_year": 1994, "from": "<an118@vox.hacktic.nl> (Nobody)", "raw_date": "Sun, 7 Aug 94 23:06:14 PDT", "to": "cypherpunks@toad.com", "reply_to": null, "message_id": "<199408080606.AA26364@xs4all.hacktic.nl>"}], "sender_id": "_an118_at_vox_hacktic_nl_nobody_"}