{"count": 12, "from": "A1 ray arachelian (library)  <rarachel@ishara.poly.edu>", "threads": [{"message_hash": "bfaa8e0abede0ce0e56e7c0b6e52e719f1410dc8181b57fb6e352e7959586ed6", "date": 739409594, "no_parent": null, "children": [{"message_hash": "44306038b06ae8bfffad89d36fc9cb7dc1bf9d93b6395c3e8ea841f7da83ba49", "date": 739415273, "no_parent": null, "children": [], "subject": "Re: ROT-13 hoopla on EchoMac", "file_year": 1993, "from": "Stanton McCandlish <anton@hydra.unm.edu>", "raw_date": "Sun, 6 Jun 93 18:07:53 PDT", "to": "rarachel@ishara.poly.edu (A1 ray arachelian)", "reply_to": "<9306070028.AA17913@ishara.poly.edu>", "message_id": "<9306070107.AA02107@hydra.unm.edu>"}], "subject": "ROT-13 hoopla on EchoMac", "file_year": 1993, "from": "A1 ray arachelian (library)  <rarachel@ishara.poly.edu>", "raw_date": "Sun, 6 Jun 93 16:33:14 PDT", "to": "cypherpunks@toad.com", "reply_to": null, "message_id": "<9306070028.AA17913@ishara.poly.edu>"}, {"message_hash": "c2128938f314d9401dac7a513c8d93b5cc1a6eb3fc5578ba5b8ab060830c90a2", "date": 739513919, "no_parent": null, "children": [{"message_hash": "c46a31b266759bbac14ce3b1e95aae81e3857608a1df73696ec6cb5562cbece6", "date": 739514951, "no_parent": null, "children": [{"message_hash": "87591ac63e665af11c5fd61d9751e0f523492663bf09f786c5c53f8e725ded13", "date": 739555415, "no_parent": null, "children": [{"message_hash": "b2b1d3baca5c0b58145441769e94d8617ea0e13ddd78c68471f89d1d71622850", "date": 739557376, "no_parent": null, "children": [], "subject": "Re: rot-13 on echomac", "file_year": 1993, "from": "pozar@kumr.lns.com (Tim Pozar)", "raw_date": "Tue, 8 Jun 93 09:36:16 PDT", "to": "composer@Beyond.Dreams.ORG (Jeff Kellem)", "reply_to": "<9306081603.AA05678@Beyond.Dreams.ORG>", "message_id": "<m0o36eT-0001w3C@kumr.lns.com>"}], "subject": "Re: rot-13 on echomac", "file_year": 1993, "from": "composer@Beyond.Dreams.ORG (Jeff Kellem)", "raw_date": "Tue, 8 Jun 93 09:03:35 PDT", "to": "pozar@kumr.lns.com (Tim Pozar)", "reply_to": "<m0o2vcI-0002cBC@kumr.lns.com>", "message_id": "<9306081603.AA05678@Beyond.Dreams.ORG>"}], "subject": "Re: rot-13 on echomac", "file_year": 1993, "from": "pozar@kumr.lns.com (Tim Pozar)", "raw_date": "Mon, 7 Jun 93 21:49:11 PDT", "to": "rarachel@ishara.poly.edu (A1 ray arachelian)", "reply_to": "<9306080527.AA23908@ishara.poly.edu>", "message_id": "<m0o2vcI-0002cBC@kumr.lns.com>"}], "subject": "Re: rot-13 on echomac", "file_year": 1993, "from": "A1 ray arachelian (library)  <rarachel@ishara.poly.edu>", "raw_date": "Mon, 7 Jun 93 21:31:59 PDT", "to": "cypherpunks@toad.com", "reply_to": null, "message_id": "<9306080527.AA23908@ishara.poly.edu>"}, {"message_hash": "1f4515f83ac82c246c3d8311ff86829c021bb3b9beca7a05a1e9c8159a41302c", "date": 745227177, "no_parent": null, "children": [{"message_hash": "8604d571e085fb720b77406c8466b75a6a4a90e699fb39e0258fd0c3abc4f26b", "date": 745229300, "no_parent": null, "children": [{"message_hash": "70c6178a016501e771065b8c8507165d199b5705f2312a116a39c51d75bc5ce8", "date": 745230776, "no_parent": null, "children": [{"message_hash": "876ac637c9d58835f98ebb55c9b9c713e7f11c99e979cb2dff0ed194dc155e12", "date": 745268577, "no_parent": null, "children": [], "subject": "one person's speculation is another's insurance hike", "file_year": 1993, "from": "andrew m. boardman <amb@cs.columbia.edu>", "raw_date": "Fri, 13 Aug 93 12:02:57 PDT", "to": "cypherpunks@toad.com", "reply_to": "<9308130831.AA12898@netcom5.netcom.com>", "message_id": "<199308131900.AA11607@ground.cs.columbia.edu>"}], "subject": "T R A F F I C  C I T A T I O N", "file_year": 1993, "from": "tcmay@netcom.com (Timothy C. May)", "raw_date": "Fri, 13 Aug 93 01:32:56 PDT", "to": "cypherpunks@toad.com", "reply_to": "<9308130806.AA01571@netcom4.netcom.com>", "message_id": "<9308130831.AA12898@netcom5.netcom.com>"}, {"message_hash": "6840d79a6e9cc7a0f570c5722541fb5ba94f1ecf7201327d7a4677ec822af599", "date": 745253578, "no_parent": null, "children": [{"message_hash": "a9951d3fbf56120c20dd7939030cee5d7eff3d27c26787bcf358f19f7e376bd6", "date": 745264107, "no_parent": null, "children": [], "subject": "Beepers can also be used to track you down!", "file_year": 1993, "from": "karn@qualcomm.com (Phil Karn)", "raw_date": "Fri, 13 Aug 93 10:48:27 PDT", "to": "rarachel@ishara.poly.edu", "reply_to": "<9308131050.AA28463@ishara.poly.edu>", "message_id": "<9308131744.AA21446@servo>"}, {"message_hash": "6f129f9454309ab54d82118dc467bfac2df9c654dc562cbf9762c3a9954b02ac", "date": 745265577, "no_parent": null, "children": [{"message_hash": "dfba2892434129300ace531a2f68353005ce7f0e3f646af4b3c041a6115787d3", "date": 745271579, "no_parent": null, "children": [], "subject": "Re: Beepers can also be used to track you down!", "file_year": 1993, "from": "rarachel@photon.poly.edu (Aarsen Ray Arachelian)", "raw_date": "Fri, 13 Aug 93 12:52:59 PDT", "to": "jet@netcom.com (J. Eric Townsend)", "reply_to": "<9308131809.AA17666@netcom.netcom.com>", "message_id": "<9308131951.AA02119@photon.poly.edu>"}], "subject": "Beepers can also be used to track you down!", "file_year": 1993, "from": "jet@netcom.com (J. Eric Townsend)", "raw_date": "Fri, 13 Aug 93 11:12:57 PDT", "to": "cypherpunks@toad.com", "reply_to": "<9308131050.AA28463@ishara.poly.edu>", "message_id": "<9308131809.AA17666@netcom.netcom.com>"}], "subject": "Beepers can also be used to track you down!", "file_year": 1993, "from": "A1 ray arachelian (library)  <rarachel@ishara.poly.edu>", "raw_date": "Fri, 13 Aug 93 07:52:58 PDT", "to": "szabo@netcom.com (Nick Szabo)", "reply_to": "<9308130806.AA01571@netcom4.netcom.com>", "message_id": "<9308131050.AA28463@ishara.poly.edu>"}], "subject": "Re: [uk.transport] Speed Camera with OCR", "file_year": 1993, "from": "szabo@netcom.com (Nick Szabo)", "raw_date": "Fri, 13 Aug 93 01:08:20 PDT", "to": "jonb@isltd.insignia.com (jon barber)", "reply_to": "<3877.9308130728@panacea.insignia.co.uk>", "message_id": "<9308130806.AA01571@netcom4.netcom.com>"}, {"message_hash": "5d6f403b5be1c256dde76e96c164b01d9012e4654e0a4bb132136dab33ec05cd", "date": 745229306, "no_parent": null, "children": [], "subject": "[uk.transport] Speed Camera with OCR", "file_year": 1993, "from": "karn@qualcomm.com (Phil Karn)", "raw_date": "Fri, 13 Aug 93 01:08:26 PDT", "to": "jonb@isltd.insignia.com", "reply_to": "<3877.9308130728@panacea.insignia.co.uk>", "message_id": "<9308130806.AA17560@servo>"}, {"message_hash": "c24bb05f568aa387a796c170b16edad360aa76fd7a08d0317c3f19f024c1ff8c", "date": 745253906, "no_parent": null, "children": [], "subject": "Re: [uk.transport] Speed Camera with OCR", "file_year": 1993, "from": "A1 ray arachelian (library)  <rarachel@ishara.poly.edu>", "raw_date": "Fri, 13 Aug 93 07:58:26 PDT", "to": "jonb@isltd.insignia.com (jon barber)", "reply_to": "<3877.9308130728@panacea.insignia.co.uk>", "message_id": "<9308131054.AA28483@ishara.poly.edu>"}], "subject": "Re: [uk.transport] Speed Camera with OCR", "file_year": 1993, "from": "jon barber <jonb@isltd.insignia.com>", "raw_date": "Fri, 13 Aug 93 00:32:57 PDT", "to": "cypherpunks@toad.com", "reply_to": null, "message_id": "<3877.9308130728@panacea.insignia.co.uk>"}, {"message_hash": "ed96ba7d195c8066ab620f4390a0e69974abf03f1cf2d9a70d481e0b524f5b87", "date": 745277909, "no_parent": null, "children": [{"message_hash": "a16e619b1f65f088ca724982db797d04875779ef42f15f8dd6e49c4c8d045438", "date": 745356104, "no_parent": null, "children": [{"message_hash": "06fc3b8770fe0d2a25134f20213a37b6b328fbd7d09136eb2b9d0f6cdbab3154", "date": 745386112, "no_parent": null, "children": [{"message_hash": "e94c6de53c0f071afe04ff1753debec46547b0c2f89773e792e2f9bd5dbf2ebd", "date": 745441616, "no_parent": null, "children": [], "subject": "Re: Beepers can also be used to track you down!", "file_year": 1993, "from": "jet@netcom.com (J. Eric Townsend)", "raw_date": "Sun, 15 Aug 93 12:06:56 PDT", "to": "A1 ray arachelian (library) <rarachel@ishara.poly.edu>", "reply_to": "<9308142338.AA05358@ishara.poly.edu>", "message_id": "<9308151905.AA18939@netcom2.netcom.com>"}], "subject": "Re: Beepers can also be used to track you down!", "file_year": 1993, "from": "A1 ray arachelian (library)  <rarachel@ishara.poly.edu>", "raw_date": "Sat, 14 Aug 93 20:41:52 PDT", "to": "jet@netcom.com (J. Eric Townsend)", "reply_to": "<9308141917.AA00520@netcom2.netcom.com>", "message_id": "<9308142338.AA05358@ishara.poly.edu>"}], "subject": "Re: Beepers can also be used to track you down!", "file_year": 1993, "from": "jet@netcom.com (J. Eric Townsend)", "raw_date": "Sat, 14 Aug 93 12:21:44 PDT", "to": "wcs@anchor.ho.att.com (Bill_Stewart(HOY002)1305)", "reply_to": "<9308132123.AA26208@anchor.ho.att.com>", "message_id": "<9308141917.AA00520@netcom2.netcom.com>"}], "subject": "Re: Beepers can also be used to track you down!", "file_year": 1993, "from": "wcs@anchor.ho.att.com (Bill_Stewart(HOY002)1305)", "raw_date": "Fri, 13 Aug 93 14:38:29 PDT", "to": "hkhenson@cup.portal.com", "reply_to": null, "message_id": "<9308132123.AA26208@anchor.ho.att.com>"}, {"message_hash": "0bf27969fbb72c62c72ba2efefcd431d2b28a8174b9767bd5f65699922af3947", "date": 748377091, "no_parent": null, "children": [{"message_hash": "9ea438e6347e4155c05b631311810dce90858f10acb05f3575f34aa43de9d4a0", "date": 748378231, "no_parent": null, "children": [{"message_hash": "8f21e0f05937f1ef58380299ac68346cce466f76e93bbeed7c197b04851565d6", "date": 748379492, "no_parent": null, "children": [], "subject": "Re: Does this seem illegal to you?", "file_year": 1993, "from": "tcmay@netcom.com (Timothy C. May)", "raw_date": "Sat, 18 Sep 93 12:11:32 PDT", "to": "rarachel@ishara.poly.edu (A1 ray arachelian)", "reply_to": "<9309181446.AA06998@ishara.poly.edu>", "message_id": "<9309181909.AA05282@netcom5.netcom.com>"}], "subject": "Re: Does this seem illegal to you?", "file_year": 1993, "from": "A1 ray arachelian (library)  <rarachel@ishara.poly.edu>", "raw_date": "Sat, 18 Sep 93 11:50:31 PDT", "to": "rees@cs.bu.edu (David Rees)", "reply_to": "<9309181829.AA17045@csa.bu.edu>", "message_id": "<9309181446.AA06998@ishara.poly.edu>"}, {"message_hash": "6cc86c4b522330585d08de9b2cb15c7e07722adb5b349e9707e12e184b3501e4", "date": 748378831, "no_parent": null, "children": [], "subject": "Re: Does this seem illegal to you?", "file_year": 1993, "from": "tcmay@netcom.com (Timothy C. May)", "raw_date": "Sat, 18 Sep 93 12:00:31 PDT", "to": "rees@cs.bu.edu (David Rees)", "reply_to": "<9309181829.AA17045@csa.bu.edu>", "message_id": "<9309181859.AA04438@netcom5.netcom.com>"}], "subject": "Does this seem illegal to you?", "file_year": 1993, "from": "rees@cs.bu.edu (David Rees)", "raw_date": "Sat, 18 Sep 93 11:31:31 PDT", "to": "cypherpunks@toad.com", "reply_to": null, "message_id": "<9309181829.AA17045@csa.bu.edu>"}, {"message_hash": "9d3f59375f63ede0805ab03d86c41fd33a1a41cbbbb979413cf2c6bbad2aee1c", "date": 749033458, "no_parent": null, "children": [{"message_hash": "0b554c72653c4e68ee5b2083bc4b8389790d83234185e62602b13443275be471", "date": 749034659, "no_parent": null, "children": [], "subject": "Re: saturation tactics?", "file_year": 1993, "from": "\"Christian D. Odhner\" <cdodhner@indirect.com>", "raw_date": "Sun, 26 Sep 93 02:10:59 PDT", "to": "gg@well.sf.ca.us (George A. Gleason)", "reply_to": "<93Sep26.015035pdt.14005-3@well.sf.ca.us>", "message_id": "<199309260908.AA07538@indirect.com>"}, {"message_hash": "bb322b1fca33a2f8d443dd6b5324bc9618a97b5550f008ea16165f6730958328", "date": 749079963, "no_parent": null, "children": [], "subject": "Re: saturation tactics?", "file_year": 1993, "from": "A1 ray arachelian (library)  <rarachel@ishara.poly.edu>", "raw_date": "Sun, 26 Sep 93 14:46:03 PDT", "to": "gg@well.sf.ca.us (George A. Gleason)", "reply_to": "<93Sep26.015035pdt.14005-3@well.sf.ca.us>", "message_id": "<9309261741.AA09655@ishara.poly.edu>"}, {"message_hash": "ae47b5c2f6fb87793eac90ed6ce5d6f8391c84bfcd20f624db2a89b044814142", "date": 749140574, "no_parent": null, "children": [], "subject": "Re: saturation tactics?", "file_year": 1993, "from": "Michael Johnson <mpjohnso@nyx.cs.du.edu>", "raw_date": "Mon, 27 Sep 93 07:36:14 PDT", "to": "\"George A. Gleason\" <gg@well.sf.ca.us>", "reply_to": "<93Sep26.015035pdt.14005-3@well.sf.ca.us>", "message_id": "<Pine.3.05.9309270849.C26891-a100000@nyx>"}], "subject": "saturation tactics?", "file_year": 1993, "from": "\"George A. Gleason\" <gg@well.sf.ca.us>", "raw_date": "Sun, 26 Sep 93 01:50:58 PDT", "to": "cypherpunks@toad.com", "reply_to": null, "message_id": "<93Sep26.015035pdt.14005-3@well.sf.ca.us>"}, {"message_hash": "75abf02b2f39c74293179b37ac0dea6f89198954cdcbebe35e1032e49180c271", "date": 750134969, "no_parent": null, "children": [{"message_hash": "f0a65b0b332a0d49f7217ad88bdd3e913c407e6ee3a604ec685bcc497c9f5d17", "date": 750136769, "no_parent": null, "children": [], "subject": "Re: Cypherpunk Cause", "file_year": 1993, "from": "ferguson@icm1.icp.net (Paul Ferguson x2044)", "raw_date": "Fri, 8 Oct 93 20:19:29 PDT", "to": "DON_HENSON@delphi.com", "reply_to": "<01H3VXEBY9AG9353JT@delphi.com>", "message_id": "<9310090415.AA17106@icm1.icp.net>"}, {"message_hash": "65b3c5366ac6caeb62fa684e92d2550a079835f0de0b4e41e2d88f4557302bc5", "date": 750215459, "no_parent": null, "children": [], "subject": "Re: Cypherpunk Cause", "file_year": 1993, "from": "A1 ray arachelian (library)  <rarachel@ishara.poly.edu>", "raw_date": "Sat, 9 Oct 93 18:10:59 PDT", "to": "DON_HENSON@delphi.com", "reply_to": "<01H3VXEBY9AG9353JT@delphi.com>", "message_id": "<9310092105.AA03310@ishara.poly.edu>"}], "subject": "Cypherpunk Cause", "file_year": 1993, "from": "DON_HENSON@delphi.com", "raw_date": "Fri, 8 Oct 93 19:49:29 PDT", "to": "cypherpunks@toad.com", "reply_to": null, "message_id": "<01H3VXEBY9AG9353JT@delphi.com>"}, {"message_hash": "b631137e5df9d15561f07d24889f7ea03fd09c53a5bcd8b2ebaf53d7c8a15dad", "date": 751931047, "no_parent": null, "children": [{"message_hash": "a096b4365712a82e35116fb82cd0a4bbae3d40024206a55983e72bf1d0432c9b", "date": 752271001, "no_parent": null, "children": [{"message_hash": "0cbdf8802cbca28f0d74d72ac1c397509dc8c7b9adae6c21650665d6d596d81a", "date": 752305337, "no_parent": null, "children": [], "subject": "Re: Style Analysis", "file_year": 1993, "from": "A1 ray arachelian (library)  <rarachel@ishara.poly.edu>", "raw_date": "Tue, 2 Nov 93 21:42:17 PST", "to": "ptaylor@panix.com (Phil Taylor)", "reply_to": "<Pine.3.05.9311021455.A12868-a100000@panix.com>", "message_id": "<9311030137.AA11763@ishara.poly.edu>"}], "subject": "Re: Style Analysis", "file_year": 1993, "from": "Phil Taylor <ptaylor@panix.com>", "raw_date": "Tue, 2 Nov 93 12:10:01 PST", "to": "Dark <unicorn@access.digex.net>", "reply_to": "<199310292142.AA22002@access.digex.net>", "message_id": "<Pine.3.05.9311021455.A12868-a100000@panix.com>"}], "subject": "Style Analysis", "file_year": 1993, "from": "Dark <unicorn@access.digex.net>", "raw_date": "Fri, 29 Oct 93 14:44:07 PDT", "to": "cypherpunks@toad.com", "reply_to": null, "message_id": "<199310292142.AA22002@access.digex.net>"}, {"message_hash": "d2416a2dfe1403f56bdfd4fed9f39c54839614f78c65e6ea74abb017d39160a4", "date": 752792903, "no_parent": null, "children": [], "subject": "If you've seen any of my posts", "file_year": 1993, "from": "A1 ray arachelian (library)  <rarachel@ishara.poly.edu>", "raw_date": "Mon, 8 Nov 93 13:08:23 PST", "to": "cypherpunks@toad.com", "reply_to": null, "message_id": "<9311081702.AA03864@ishara.poly.edu>"}, {"message_hash": "0ea8a2f474be4c6080739fe26d910e1f54b04cf19203fb9a2e7f9922b1ac8b65", "date": 752620965, "no_parent": null, "children": [{"message_hash": "460fdb1c1508b5f1a62cb92290b2ea3d42b13b6ea8873ea79b0fac8e5e95a48a", "date": 752684591, "no_parent": null, "children": [], "subject": "Re: Mark Abene (Phiber Optik) sentenced", "file_year": 1993, "from": "Mike Godwin <mnemonic@eff.org>", "raw_date": "Sun, 7 Nov 93 07:03:11 PST", "to": "ferguson@icm1.icp.net (Paul Ferguson x2044)", "reply_to": "<9311062120.AA09817@icm1.icp.net>", "message_id": "<199311071502.AA00947@eff.org>"}, {"message_hash": "0fa76e34242f73c8ea29a3c1c3ff558bd027de8d34a7d11f101cd52b81a8abab", "date": 752726894, "no_parent": null, "children": [{"message_hash": "e30fb44ef83bdd240dde32f249f61dab0e96c6f4384185f9843e280ed8fd653a", "date": 752735294, "no_parent": null, "children": [{"message_hash": "aaf49047cd60c2dc5628d60e1771140c01a9cfb1ebf35299728aa544b911e990", "date": 752742497, "no_parent": null, "children": [{"message_hash": "ad28c612dd2c559dea6c74774dcf4a45f2ab7f379cf2514ac801d3665d70fe09", "date": 752788103, "no_parent": null, "children": [], "subject": "Re: tapping hardware? (was re: Mark Abene (Phiber Optik) sentenced)", "file_year": 1993, "from": "Brad Huntting <huntting@glarp.com>", "raw_date": "Mon, 8 Nov 93 11:48:23 PST", "to": "Timothy Newsham <newsham@wiliki.eng.hawaii.edu>", "reply_to": "<9311080705.AA15339@toad.com>", "message_id": "<199311081947.AA09591@misc.glarp.com>"}, {"message_hash": "b4214e2dcf6549c633ceab436dd8f2f6c1176785ac395fa098a42c4689dae058", "date": 752790183, "no_parent": null, "children": [{"message_hash": "4f652051d336db988564c071c39aad250b6d302affa8ed9cb8a45d2241854df6", "date": 752792927, "no_parent": null, "children": [], "subject": "Re: Tapping modem transmissions", "file_year": 1993, "from": "A1 ray arachelian (library)  <rarachel@ishara.poly.edu>", "raw_date": "Mon, 8 Nov 93 13:08:47 PST", "to": "mg5n+@andrew.cmu.edu (Matthew J Ghio)", "reply_to": "<Ugrec5600awK8D9Uch@andrew.cmu.edu>", "message_id": "<9311081659.AA03819@ishara.poly.edu>"}], "subject": "Tapping modem transmissions", "file_year": 1993, "from": "Matthew J Ghio <mg5n+@andrew.cmu.edu>", "raw_date": "Mon, 8 Nov 93 12:23:03 PST", "to": "cypherpunks@toad.com", "reply_to": "<9311080705.AA15339@toad.com>", "message_id": "<Ugrec5600awK8D9Uch@andrew.cmu.edu>"}], "subject": "Re: tapping hardware? (was re: Mark Abene (Phiber Optik) sentenced)", "file_year": 1993, "from": "Timothy Newsham <newsham@wiliki.eng.hawaii.edu>", "raw_date": "Sun, 7 Nov 93 23:08:17 PST", "to": "kovar@nda.com (David Kovar)", "reply_to": "<199311080426.XAA29294@nda.nda.com>", "message_id": "<9311080705.AA15339@toad.com>"}], "subject": "Re: tapping hardware? (was re: Mark Abene (Phiber Optik) sentenced)", "file_year": 1993, "from": "David Kovar <kovar@nda.com>", "raw_date": "Sun, 7 Nov 93 21:08:14 PST", "to": "eichin@paycheck.cygnus.com (Mark W. Eichin)", "reply_to": "<9311062339.AA18639@paycheck.cygnus.com>", "message_id": "<199311080426.XAA29294@nda.nda.com>"}, {"message_hash": "b4367a31117c296a1d4889442bf4e898631f871f9f4d2cd4e0cdb01d4fb820d4", "date": 752753616, "no_parent": null, "children": [], "subject": "Re: tapping hardware? (was re: Mark Abene (Phiber Optik) sentenced)", "file_year": 1993, "from": "kelly@netcom.com (Kelly Goen)", "raw_date": "Mon, 8 Nov 93 02:13:36 PST", "to": "eichin@paycheck.cygnus.com (Mark W. Eichin)", "reply_to": "<9311062339.AA18639@paycheck.cygnus.com>", "message_id": "<199311081013.CAA25398@mail.netcom.com>"}], "subject": "tapping hardware? (was re: Mark Abene (Phiber Optik) sentenced)", "file_year": 1993, "from": "\"Mark W. Eichin\" <eichin@paycheck.cygnus.com>", "raw_date": "Sun, 7 Nov 93 18:48:14 PST", "to": "cypherpunks@toad.com", "reply_to": "<9311062120.AA09817@icm1.icp.net>", "message_id": "<9311062339.AA18639@paycheck.cygnus.com>"}], "subject": "Mark Abene (Phiber Optik) sentenced", "file_year": 1993, "from": "ferguson@icm1.icp.net (Paul Ferguson x2044)", "raw_date": "Sat, 6 Nov 93 13:22:45 PST", "to": "cypherpunks@toad.com", "reply_to": null, "message_id": "<9311062120.AA09817@icm1.icp.net>"}, {"message_hash": "327178f05dbc14380985f0d70b190800c5465ec08cd6792740f9da3d514f1d63", "date": 756517521, "no_parent": null, "children": [{"message_hash": "9e87835cd9faf3d57dbbb8efacc6743b3621108efa2bf8ddf801c8900e1a1a07", "date": 756597937, "no_parent": null, "children": [{"message_hash": "1b40c536de253bc9afd2c379df508621e5ee754683b8f34ad9e946ee206102d9", "date": 756598538, "no_parent": null, "children": [], "subject": "Re: Kid Scan (tm)", "file_year": 1993, "from": "Jim choate <ravage@wixer.bga.com>", "raw_date": "Wed, 22 Dec 93 14:15:38 PST", "to": "rarachel@ishara.poly.edu (A1 ray arachelian)", "reply_to": "<9312221757.AA16400@ishara.poly.edu>", "message_id": "<9312222200.AA24099@wixer>"}], "subject": "Re: Kid Scan (tm)", "file_year": 1993, "from": "A1 ray arachelian (library)  <rarachel@ishara.poly.edu>", "raw_date": "Wed, 22 Dec 93 14:05:37 PST", "to": "ravage@wixer.bga.com (Jim choate)", "reply_to": "<9312212333.AA15999@wixer>", "message_id": "<9312221757.AA16400@ishara.poly.edu>"}], "subject": "Kid Scan (tm)", "file_year": 1993, "from": "Jim choate <ravage@wixer.bga.com>", "raw_date": "Tue, 21 Dec 93 15:45:21 PST", "to": "cypherpunks@toad.com", "reply_to": null, "message_id": "<9312212333.AA15999@wixer>"}], "sender_id": "a1_ray_arachelian_library_rarachel_at_ishara_poly_edu_"}