{"count": 4, "from": "abootch@sfsuvax1.sfsu.edu (Bokum Bop Till You Drop)", "threads": [{"message_hash": "03575ebe6521ba8f1545bd82d140eb72af3b7e47ee722422b4e620c48211ab9b", "date": 752572074, "no_parent": null, "children": [], "subject": "pgp in the weirdest places!", "file_year": 1993, "from": "abootch@sfsuvax1.sfsu.edu (Bokum Bop Till You Drop)", "raw_date": "Fri, 5 Nov 93 23:47:54 PST", "to": "cypherpunks@toad.com (cypher)", "reply_to": null, "message_id": "<9311060745.AA13909@sfsuvax1.sfsu.edu>"}, {"message_hash": "1c5870869268792c438fc6c7744515adca1dee783ab8df612ebd91b0e8c08518", "date": 752969941, "no_parent": null, "children": [], "subject": "Hardware for Sale", "file_year": 1993, "from": "abootch@sfsuvax1.sfsu.edu (Bokum Bop Till You Drop)", "raw_date": "Wed, 10 Nov 93 14:19:01 PST", "to": "cypherpunks@toad.com", "reply_to": null, "message_id": "<9311102215.AA11909@sfsuvax1.sfsu.edu>"}, {"message_hash": "09c98f17d00495785eefcaac1b4ca7f7593380c40588ad99dfdf279e2dbd67ba", "date": 753035611, "no_parent": null, "children": [{"message_hash": "e5befd51badd3427d01abaf925304fab984bf0f738e9ee837c34b12f80f91e3f", "date": 753059015, "no_parent": null, "children": [], "subject": "Re: modem taps/caller id", "file_year": 1993, "from": "abootch@sfsuvax1.sfsu.edu (Bokum Bop Till You Drop)", "raw_date": "Thu, 11 Nov 93 15:03:35 PST", "to": "Martin.Greifer@f28.n125.z1.fidonet.org (Martin Greifer)", "reply_to": "<4110.2CE1DFEC@shelter.FIDONET.ORG>", "message_id": "<9311112303.AA19607@sfsuvax1.sfsu.edu>"}, {"message_hash": "89c6900bf9a943284746306299d141715aa6c1b56a587447b22535d83cab737e", "date": 753499454, "no_parent": null, "children": [], "subject": "Re: modem taps/caller id", "file_year": 1993, "from": "Stanton McCandlish <mech@eff.org>", "raw_date": "Tue, 16 Nov 93 17:24:14 PST", "to": "Martin.Greifer@f28.n125.z1.FIDONET.ORG (Martin Greifer)", "reply_to": "<4110.2CE1DFEC@shelter.FIDONET.ORG>", "message_id": "<199311170122.UAA02039@eff.org>"}], "subject": "Re: modem taps/caller id", "file_year": 1993, "from": "Martin.Greifer@f28.n125.z1.FIDONET.ORG (Martin Greifer)", "raw_date": "Thu, 11 Nov 93 08:33:31 PST", "to": "Cypherpunks@toad.com", "reply_to": null, "message_id": "<4110.2CE1DFEC@shelter.FIDONET.ORG>"}, {"message_hash": "ee5d65eb1bd04336bfd2b2b79fa2e991072ab7f05195dca1529037a601dd8b79", "date": 753059615, "no_parent": null, "children": [], "subject": "tel news", "file_year": 1993, "from": "abootch@sfsuvax1.sfsu.edu (Bokum Bop Till You Drop)", "raw_date": "Thu, 11 Nov 93 15:13:35 PST", "to": "cypherpunks@toad.com (Cypherpunks)", "reply_to": null, "message_id": "<9311112312.AA21315@sfsuvax1.sfsu.edu>"}], "sender_id": "abootch_at_sfsuvax1_sfsu_edu_bokum_bop_till_you_drop_"}