{"count": 2, "from": "\"Andrew Roos\" <ANDREWR@real3.realtime.co.za>", "threads": [{"message_hash": "7fe4d4870ec2452f56c58650cc7484801b7216a9fe97d19db56f398a85eeb151", "date": 806117997, "no_parent": null, "children": [{"message_hash": "c9c2485937e277bb6bfacc36b37d3d7b3e77cab211e5806ed512a31e3300efbe", "date": 805985843, "no_parent": null, "children": [], "subject": "Here it is; bi-directional dining cryptographers", "file_year": 1995, "from": "Phil Fraering        <pgf@tyrell.net>", "raw_date": "Mon, 17 Jul 95 05:57:23 PDT", "to": "andrewr@realtime.co.za", "reply_to": "<C189311569@real3.realtime.co.za>", "message_id": "<199507171252.AA14868@tyrell.net>"}, {"message_hash": "c812a527eac37b6042a504f8bd43af75247aef72e19c37acd36d6445246bbc6b", "date": 805985905, "no_parent": null, "children": [], "subject": "Here it is; bi-directional dining cryptographers", "file_year": 1995, "from": "Phil Fraering        <pgf@tyrell.net>", "raw_date": "Mon, 17 Jul 95 05:58:25 PDT", "to": "andrewr@realtime.co.za", "reply_to": "<C189311569@real3.realtime.co.za>", "message_id": "<199507171253.AA14941@tyrell.net>"}], "subject": "Re: Here it is; bi-directional dining cryptographers", "file_year": 1995, "from": "\"Andrew Roos\" <ANDREWR@real3.realtime.co.za>", "raw_date": "Tue, 18 Jul 95 18:39:57 PDT", "to": "Phil Fraering        <pgf@tyrell.net>", "reply_to": null, "message_id": "<C189311569@real3.realtime.co.za>"}, {"message_hash": "93f38fcd3070cac5c8e8df13f81adc82492edb6a4f66c469e4ef9c468acbdc04", "date": 806247992, "no_parent": null, "children": [], "subject": "Re: (Cracking) Netscape (is) the Big Win", "file_year": 1995, "from": "\"Andrew Roos\" <ANDREWR@real3.realtime.co.za>", "raw_date": "Thu, 20 Jul 95 06:46:32 PDT", "to": "trei@process.com", "reply_to": null, "message_id": "<10AECF4554D@real3.realtime.co.za>"}], "sender_id": "andrew_roos_andrewr_at_real3_realtime_co_za_"}