{"count": 7, "from": "Anonymous@cs.Buffalo.EDU", "threads": [{"message_hash": "7699142cd584d73eb36c1c8c8b425762cd8db7c41954b3bb0b1b4e8bf6ceef24", "date": 728700929, "no_parent": null, "children": [], "subject": "Remailer changes.", "file_year": 1993, "from": "Anonymous@cs.Buffalo.EDU", "raw_date": "Tue, 2 Feb 93 16:55:29 PST", "to": "cypherpunks@toad.com", "reply_to": null, "message_id": "<9302030054.AA17885@armstrong.cs.Buffalo.EDU>"}, {"message_hash": "8edbd3c3c5c96f6b2dcc24f4e50f50e2dd720cc9c353947cd3cef0526f73d1be", "date": 730138040, "no_parent": null, "children": [], "subject": "PGP anonymous remailer", "file_year": 1993, "from": "Anonymous@cs.Buffalo.EDU", "raw_date": "Fri, 19 Feb 93 08:07:20 PST", "to": "cypherpunks@toad.com", "reply_to": null, "message_id": "<9302191606.AA13301@armstrong.cs.Buffalo.EDU>"}, {"message_hash": "bfa5786e2ca30c0b79c8449d7de2c6f342c50897c1ac9e774b8a7cbb83827a22", "date": 730138539, "no_parent": null, "children": [], "subject": "Test the new remailer", "file_year": 1993, "from": "Anonymous@cs.Buffalo.EDU", "raw_date": "Fri, 19 Feb 93 08:15:39 PST", "to": "cypherpunks@toad.com", "reply_to": null, "message_id": "<9302191614.AA13658@armstrong.cs.Buffalo.EDU>"}, {"message_hash": "7db63a53bbc31f4d23c764fa04336e977013a6337d82b858d086163e948351a9", "date": 730228546, "no_parent": null, "children": [], "subject": "Re: anonymous mail", "file_year": 1993, "from": "Anonymous@cs.Buffalo.EDU", "raw_date": "Sat, 20 Feb 93 09:15:46 PST", "to": "cypherpunks@toad.com", "reply_to": null, "message_id": "<9302201714.AA11332@armstrong.cs.Buffalo.EDU>"}, {"message_hash": "7b6d08db7ac84433d6071f25558af27ccd4c4a50ecb5fe3fdd51b14666edaf40", "date": 730324603, "no_parent": null, "children": [], "subject": "Re: whistleblower newsgroup?", "file_year": 1993, "from": "Anonymous@cs.Buffalo.EDU", "raw_date": "Sun, 21 Feb 93 11:56:43 PST", "to": "cypherpunks@toad.com", "reply_to": null, "message_id": "<9302211955.AA12769@armstrong.cs.Buffalo.EDU>"}, {"message_hash": "dfcfe36bd1ff1010887f4c5de00767ab0a08bd481a29d49baf25093fa627f6f6", "date": 730490159, "no_parent": null, "children": [], "subject": "two copies of deadbeat's mail...", "file_year": 1993, "from": "Anonymous@cs.Buffalo.EDU", "raw_date": "Tue, 23 Feb 93 09:55:59 PST", "to": "cypherpunks@toad.com", "reply_to": null, "message_id": "<9302231754.AA16626@armstrong.cs.Buffalo.EDU>"}, {"message_hash": "8ceb04fa8b5b6586756434c83c9caf593f53258aacfb3f5ecea7a233258b0c9a", "date": 730736749, "no_parent": null, "children": [], "subject": "Was: Poor man's anon server ...", "file_year": 1993, "from": "Anonymous@cs.Buffalo.EDU", "raw_date": "Fri, 26 Feb 93 06:25:49 PST", "to": "cypherpunks@toad.com", "reply_to": null, "message_id": "<9302261424.AA22409@armstrong.cs.Buffalo.EDU>"}], "sender_id": "anonymous_at_cs_buffalo_edu"}