{"count": 1, "from": "barrk@alias.cyberpass.net (Barry K.)", "threads": [{"message_hash": "7570e0c124f15a548326916064c0999bc6cff735e5561734f47a301df6804b80", "date": 843168178, "no_parent": null, "children": [{"message_hash": "eb781eb158dad6ffc228ad902c5c30b17070cdaf7efb9be9bf1e7c463338e284", "date": 843177235, "no_parent": null, "children": [], "subject": "Unsubscribe", "file_year": 1996, "from": "Chang-Shing Perng <perng@cs.ucla.edu>", "raw_date": "Thu, 19 Sep 1996 16:53:55 -0700 (PDT)", "to": "\"Barry K.\" <barrk@alias.cyberpass.net>", "reply_to": "<199609192042.NAA16104@sirius.infonex.com>", "message_id": "<3241DBC5.4A86@cs.ucla.edu>"}], "subject": "Re: Bernstein hearing reminder: [..]", "file_year": 1996, "from": "barrk@alias.cyberpass.net (Barry K.)", "raw_date": "Thu, 19 Sep 1996 14:22:58 -0700 (PDT)", "to": "cypherpunks-announce@toad.com", "reply_to": null, "message_id": "<199609192042.NAA16104@sirius.infonex.com>"}], "sender_id": "barrk_at_alias_cyberpass_net_barry_k_"}