{"count": 28, "from": "Ben Holiday <ncognito@gate.net>", "threads": [{"message_hash": "8fb4cce82e1bc285a5988c75a5a332959f98c30cad23a3a09acba9b85a380957", "date": 816888112, "no_parent": null, "children": [{"message_hash": "65f3c355400fc9f5bf953541454586c00d5272a86b87790aa5d345ad9509fcc7", "date": 816883593, "no_parent": null, "children": [], "subject": "Re: remailer abuse", "file_year": 1995, "from": "Ben Holiday <ncognito@gate.net>", "raw_date": "Tue, 21 Nov 1995 00:06:33 +0800", "to": "remailer-operators@c2.org", "reply_to": "<199511200127.AA17430@ideath.goldenbear.com>", "message_id": "<Pine.A32.3.91.951119225404.61842A-100000@hopi.gate.net>"}], "subject": "remailer abuse", "file_year": 1995, "from": "Greg Broiles <greg@ideath.goldenbear.com>", "raw_date": "Tue, 21 Nov 1995 01:21:52 +0800", "to": "remailer-operators@c2.org", "reply_to": null, "message_id": "<199511200127.AA17430@ideath.goldenbear.com>"}, {"message_hash": "d23264b6a176207d8ae7fcf557ef1222d95d489ebe325c6aa661f1b656e6e1d3", "date": 818819493, "no_parent": null, "children": [{"message_hash": "7601613ba32f99f0d84ff7ccd1e73957f92cc4f056d3c0650b1f754f772825e0", "date": 818824548, "no_parent": null, "children": [], "subject": "Re: IDEA encryption", "file_year": 1995, "from": "\"Mark M.\" <markm@omni.voicenet.com>", "raw_date": "Wed, 13 Dec 1995 11:15:48 +0800", "to": "cypherpunks@toad.com", "reply_to": "<Pine.A32.3.91.951212174132.26320B-100000@hopi.gate.net>", "message_id": "<Pine.LNX.3.91.951212212447.94B-100000@localhost>"}, {"message_hash": "b208db9e9755ff8aa8a1eaf671c4134daef45812217e00873b7db815891858b5", "date": 818893366, "no_parent": null, "children": [{"message_hash": "6e7791e62008912e9e05f6c22f62c0bc8ea4440833b332ad14d2b1e56191af40", "date": 818934171, "no_parent": null, "children": [], "subject": "Re: IDEA encryption", "file_year": 1995, "from": "Ben Holiday <ncognito@gate.net>", "raw_date": "Thu, 14 Dec 1995 17:42:51 +0800", "to": "cypherpunks@toad.com", "reply_to": "<199512130237.VAA21019@charon.MIT.EDU>", "message_id": "<Pine.A32.3.91.951213015449.59778A-100000@hopi.gate.net>"}], "subject": "Re: IDEA encryption", "file_year": 1995, "from": "Derek Atkins <warlord@ATHENA.MIT.EDU>", "raw_date": "Thu, 14 Dec 1995 06:22:46 +0800", "to": "Ben Holiday <ncognito@gate.net>", "reply_to": "<Pine.A32.3.91.951212174132.26320B-100000@hopi.gate.net>", "message_id": "<199512130237.VAA21019@charon.MIT.EDU>"}], "subject": "IDEA encryption", "file_year": 1995, "from": "Ben Holiday <ncognito@gate.net>", "raw_date": "Wed, 13 Dec 1995 09:51:33 +0800", "to": "cypherpunks@toad.com", "reply_to": null, "message_id": "<Pine.A32.3.91.951212174132.26320B-100000@hopi.gate.net>"}, {"message_hash": "fbfa688a3fedb049743dfe364532137b888e31c00fcb735c89e8f360cc186496", "date": 819091260, "no_parent": 1, "children": [{"message_hash": "0d705d23a4dedd3373f4f579e3087b5507812ee1fc5259016c11a1a3b0413487", "date": 819019912, "no_parent": null, "children": [], "subject": "Re: Secured RM ? (source)", "file_year": 1995, "from": "Ben Holiday <ncognito@gate.net>", "raw_date": "Fri, 15 Dec 1995 17:31:52 +0800", "to": "cypherpunks@toad.com", "reply_to": "<199512150218.VAA14539@homeport.org>", "message_id": "<Pine.A32.3.91.951214222509.43804A-100000@hopi.gate.net>"}], "subject": "Re: Secured RM ? (source)", "file_year": 1995, "from": "Adam Shostack <adam@lighthouse.homeport.org>", "raw_date": "Sat, 16 Dec 1995 13:21:00 +0800", "to": "root@HellSpawn.gate.net (root)", "reply_to": "<Pine.LNX.3.91.800121064335.1068A-100000@HellSpawn.gate.net>", "message_id": "<199512150218.VAA14539@homeport.org>"}, {"message_hash": "959a7328daee041e689186973f2eedfe03007a53b260a8f296b522b013c1b2d8", "date": 819040208, "no_parent": 1, "children": [{"message_hash": "84a1a1f1a39c15671ce15b502851bf102f5b3dc58bee0509ac88777eaa5226bf", "date": 819176284, "no_parent": null, "children": [{"message_hash": "a74e28a87cef9aac47a0d3e28a75b0fbaa83f465f50ebd994042e2e081130a20", "date": 819196667, "no_parent": null, "children": [], "subject": "Re: Secured RM ? (source)", "file_year": 1995, "from": "Ben Holiday <ncognito@gate.net>", "raw_date": "Sun, 17 Dec 1995 18:37:47 +0800", "to": "cypherpunks@toad.com", "reply_to": "<199512170428.PAA22362@sweeney.cs.monash.edu.au>", "message_id": "<Pine.A32.3.91.951217051339.43966A-100000@hopi.gate.net>"}], "subject": "Re: Secured RM ? (source)", "file_year": 1995, "from": "Jiri Baum <jirib@sweeney.cs.monash.edu.au>", "raw_date": "Sun, 17 Dec 1995 12:58:04 +0800", "to": "jps@monad.semcor.com (Jack P. Starrantino)", "reply_to": "<9512151425.AA07871@monad.semcor.com>", "message_id": "<199512170428.PAA22362@sweeney.cs.monash.edu.au>"}], "subject": "Re: Secured RM ? (source)", "file_year": 1995, "from": "jps@monad.semcor.com (Jack P. Starrantino)", "raw_date": "Fri, 15 Dec 1995 23:10:08 +0800", "to": "cypherpunks@toad.com", "reply_to": "<Pine.LNX.3.91.800121064335.1068A-100000@HellSpawn.gate.net>", "message_id": "<9512151425.AA07871@monad.semcor.com>"}, {"message_hash": "9ce30fe8a2fb6a3afe5d7a0e7f26065155f35ac3e337f6e1fb3504a364355a66", "date": 819277960, "no_parent": 1, "children": [], "subject": "Re: Secured RM ? (source)", "file_year": 1995, "from": "Ben Holiday <ncognito@gate.net>", "raw_date": "Mon, 18 Dec 1995 17:12:40 +0800", "to": "cypherpunks@toad.com", "reply_to": "<199512171048.VAA23204@sweeney.cs.monash.edu.au>", "message_id": "<Pine.A32.3.91.951218004301.41900A-100000@hopi.gate.net>"}, {"message_hash": "99ef93c0130fdf3c5447ed8d6a702219b842aa43b3f907a15f315a673afe77bb", "date": 819321186, "no_parent": null, "children": [{"message_hash": "53808bbc343eb844363c60b038203917398a4e7ce83a7d00670c3b592ff8d274", "date": 819303948, "no_parent": null, "children": [], "subject": "Re: redirect of newsgroups", "file_year": 1995, "from": "\"Perry E. Metzger\" <perry@piermont.com>", "raw_date": "Tue, 19 Dec 1995 00:25:48 +0800", "to": "\"David Klur\" <dklur@dttus.com>", "reply_to": "<9511188193.AA819305757@cc2.dttus.com>", "message_id": "<199512181543.KAA09973@jekyll.piermont.com>"}, {"message_hash": "6c143003999f211048e65811717b8e9586404325a28979c94f17b3f8abebb008", "date": 819343972, "no_parent": null, "children": [{"message_hash": "8b3a1385032e3af17e1e35fc9fc5ee990b4b5db7bd581803917e486323df6ef8", "date": 819366374, "no_parent": null, "children": [], "subject": "Re: redirect of newsgroups", "file_year": 1995, "from": "Ben Holiday <ncognito@gate.net>", "raw_date": "Tue, 19 Dec 1995 17:46:14 +0800", "to": "cypherpunks@toad.com", "reply_to": "<199512190221.VAA20286@homeport.org>", "message_id": "<Pine.A32.3.91.951219003649.70364A-100000@navajo.gate.net>"}], "subject": "Re: redirect of newsgroups", "file_year": 1995, "from": "Adam Shostack <adam@lighthouse.homeport.org>", "raw_date": "Tue, 19 Dec 1995 11:32:52 +0800", "to": "dklur@dttus.com (David Klur)", "reply_to": "<9511188193.AA819305757@cc2.dttus.com>", "message_id": "<199512190221.VAA20286@homeport.org>"}], "subject": "redirect of newsgroups", "file_year": 1995, "from": "\"David Klur\" <dklur@dttus.com>", "raw_date": "Tue, 19 Dec 1995 05:13:06 +0800", "to": "cypherpunks@toad.com", "reply_to": null, "message_id": "<9511188193.AA819305757@cc2.dttus.com>"}, {"message_hash": "d5103d1377dc3ea2d9cb36ecaf0d1ec3cb95646c06a37de4cc551d265a8a010a", "date": 825980739, "no_parent": null, "children": [{"message_hash": "1dd23c8a2c165434bc9f71273365f4d0337f077b3fc40a784acc1f6db3998e3d", "date": 826102778, "no_parent": null, "children": [{"message_hash": "e412c2e4bb83af780bc240f7627a084b1ac62a68a04cae64bc3cfb89e4b04abb", "date": 826122506, "no_parent": null, "children": [], "subject": "Re: Steganography idea: CU-SeeMe", "file_year": 1996, "from": "Ed Carp <erc@dal1820.computek.net>", "raw_date": "Wed, 6 Mar 96 06:28:26 PST", "to": "Nelson Minar <nelson@santafe.edu>", "reply_to": "<199603060734.AAA00178@nelson.santafe.edu>", "message_id": "<Pine.3.89.9603060803.B1536-0100000@dal1820.computek.net>"}, {"message_hash": "14c32515264aa465e306b5f574fb2749ed5d9b90dab903691b4299427d4d9d6b", "date": 826316967, "no_parent": null, "children": [{"message_hash": "c1946b5d23eea129e62a764007685bbecb0e539267eafd16c34c349ab3c47b5e", "date": 826220243, "no_parent": null, "children": [], "subject": "Re: Steganography idea: CU-SeeMe", "file_year": 1996, "from": "Ben Holiday <ncognito@gate.net>", "raw_date": "Fri, 8 Mar 1996 01:37:23 +0800", "to": "cypherpunks@toad.com", "reply_to": "<199603061134.MAA17301@utopia.hacktic.nl>", "message_id": "<Pine.A32.3.91.960306173520.65536B-100000@hopi.gate.net>"}], "subject": "Re: Steganography idea: CU-SeeMe", "file_year": 1996, "from": "anon-remailer@utopia.hacktic.nl (Anonymous)", "raw_date": "Sat, 9 Mar 1996 04:29:27 +0800", "to": "cypherpunks@toad.com", "reply_to": "<199603060734.AAA00178@nelson.santafe.edu>", "message_id": "<199603061134.MAA17301@utopia.hacktic.nl>"}], "subject": "Steganography idea: CU-SeeMe", "file_year": 1996, "from": "Nelson Minar <nelson@santafe.edu>", "raw_date": "Wed, 6 Mar 1996 16:59:38 +0800", "to": "cypherpunks@toad.com", "reply_to": "<9603041921.AA08825@bilbo.suite.com>", "message_id": "<199603060734.AAA00178@nelson.santafe.edu>"}], "subject": "art-stego", "file_year": 1996, "from": "jim@bilbo.suite.com (Jim Miller)", "raw_date": "Tue, 5 Mar 1996 07:05:39 +0800", "to": "cypherpunks@toad.com", "reply_to": null, "message_id": "<9603041921.AA08825@bilbo.suite.com>"}, {"message_hash": "7449f34a00011b90baf83f4f3ee34e375d264a9f7eb31d07747cb69d7f1486ac", "date": 826466130, "no_parent": null, "children": [], "subject": "TCP/IP Stego (was CU-SeeMe)", "file_year": 1996, "from": "Ben Holiday <ncognito@gate.net>", "raw_date": "Sun, 10 Mar 1996 21:55:30 +0800", "to": "cypherpunks@toad.com", "reply_to": null, "message_id": "<Pine.A32.3.91.960307010925.29850B-100000@seminole.gate.net>"}, {"message_hash": "efb183d623df8374eb1bf4df644620201b52f60988f1c293d0998f6dd332b66c", "date": 826511000, "no_parent": null, "children": [{"message_hash": "0c0334b4f6d12c93d7e677dc118e4eb0f04442a58e7c9fe23e13151ceaf8d744", "date": 826492971, "no_parent": null, "children": [], "subject": "Re: TCP/IP Stego (was CU-SeeMe)", "file_year": 1996, "from": "Ben Holiday <ncognito@gate.net>", "raw_date": "Mon, 11 Mar 1996 05:22:51 +0800", "to": "cypherpunks@toad.com", "reply_to": "<199603082056.MAA20781@netcom7.netcom.com>", "message_id": "<Pine.A32.3.91.960309005518.27482B-100000@seminole.gate.net>"}], "subject": "Re: TCP/IP Stego (was CU-SeeMe)", "file_year": 1996, "from": "frantz@netcom.com (Bill Frantz)", "raw_date": "Mon, 11 Mar 1996 10:23:20 +0800", "to": "cypherpunks@toad.com", "reply_to": null, "message_id": "<199603082056.MAA20781@netcom7.netcom.com>"}, {"message_hash": "2ddc48db081b2500da6909bd29656e16a905752a8bd3f8e996b45cb83285311b", "date": 826557116, "no_parent": null, "children": [{"message_hash": "0b0f6773d737e2d441a06eab7c508a37de711050e0415bc76c72cb0d591fa0c3", "date": 826650403, "no_parent": null, "children": [], "subject": "Remail Software Where?", "file_year": 1996, "from": "Ben Holiday <ncognito@gate.net>", "raw_date": "Wed, 13 Mar 1996 01:06:43 +0800", "to": "Raph Levien <raph@CS.Berkeley.EDU>", "reply_to": "<199603111450.GAA01786@kiwi.cs.berkeley.edu>", "message_id": "<Pine.A32.3.91.960311183748.33978A-100000@hopi.gate.net>"}], "subject": "List of reliable remailers", "file_year": 1996, "from": "Raph Levien <raph@CS.Berkeley.EDU>", "raw_date": "Mon, 11 Mar 1996 23:11:56 +0800", "to": "cypherpunks@toad.com", "reply_to": null, "message_id": "<199603111450.GAA01786@kiwi.cs.berkeley.edu>"}, {"message_hash": "8b7bfb04f2bf162c16b4e0dd8952c420fde6c9dc60752a5983f14516346ef106", "date": 827662915, "no_parent": null, "children": [{"message_hash": "4f07d35b35e71b2bee1ca525e9a063665c5d937f85301fede395eef92106a59a", "date": 827688934, "no_parent": null, "children": [], "subject": "Re: Crypto CD", "file_year": 1996, "from": "Adam Shostack <adam@lighthouse.homeport.org>", "raw_date": "Mon, 25 Mar 1996 01:35:34 +0800", "to": "ncognito@gate.net (Ben Holiday)", "reply_to": "<Pine.A32.3.91.960324013306.50010C-100000@hopi.gate.net>", "message_id": "<199603241717.MAA25157@homeport.org>"}], "subject": "Crypto CD", "file_year": 1996, "from": "Ben Holiday <ncognito@gate.net>", "raw_date": "Sun, 24 Mar 1996 18:21:55 +0800", "to": "cypherpunks@toad.com", "reply_to": null, "message_id": "<Pine.A32.3.91.960324013306.50010C-100000@hopi.gate.net>"}, {"message_hash": "37f827193c3d8713448373b0247391b3fd9998d93b2d162dd1f5f719a1657201", "date": 831556638, "no_parent": null, "children": [{"message_hash": "2990e800c72e756cbd1459b7712ee5d53b261feac218a643825f97909c527ef7", "date": 831742520, "no_parent": null, "children": [], "subject": "Re: remailer-in-a-box", "file_year": 1996, "from": "Ben Holiday <ncognito@gate.net>", "raw_date": "Fri, 10 May 1996 23:35:20 +0800", "to": "Lance Cottrell <loki@infonex.com>", "reply_to": "<adb5ec01090210047acd@[206.170.115.3]>", "message_id": "<Pine.A32.3.93.960509105054.31020A-100000@hopi.gate.net>"}], "subject": "Re: remailer-in-a-box", "file_year": 1996, "from": "loki@infonex.com (Lance Cottrell)", "raw_date": "Wed, 8 May 1996 19:57:18 +0800", "to": "cypherpunks@toad.com", "reply_to": null, "message_id": "<adb5ec01090210047acd@[206.170.115.3]>"}, {"message_hash": "0fee87f6375744634f53107313d0cbcad79074c3b4cabbc3ab186ace8093fde1", "date": 832678101, "no_parent": 1, "children": [{"message_hash": "bdd1599408433a74d98eb7bd1b7e9f4c9861173ef6430e531ddd31d45b5b42e3", "date": 832686750, "no_parent": null, "children": [{"message_hash": "2d37bb748898257ff861e1cee480b854976ae772605078145d00f1179f224398", "date": 832687352, "no_parent": null, "children": [], "subject": "Re: An alternative to remailer shutdowns", "file_year": 1996, "from": "Rich Graves <llurch@networking.stanford.edu>", "raw_date": "Tue, 21 May 1996 22:02:32 +0800", "to": "jonathon <grafolog@netcom.com>", "reply_to": "<Pine.3.89.9605210818.A20379-0100000@netcom3>", "message_id": "<Pine.GUL.3.93.960521011638.4377B-100000@Networking.Stanford.EDU>"}], "subject": "Re: An alternative to remailer shutdowns", "file_year": 1996, "from": "jonathon <grafolog@netcom.com>", "raw_date": "Tue, 21 May 1996 21:52:30 +0800", "to": "Rich Graves <llurch@networking.stanford.edu>", "reply_to": "<Pine.GUL.3.93.960520223851.489X-100000@Networking.Stanford.EDU>", "message_id": "<Pine.3.89.9605210818.A20379-0100000@netcom3>"}, {"message_hash": "0a809d95e16fa8f6db63798f4e2ae9b3fea6e6a82a77fb7aa7494314ab30942d", "date": 832730873, "no_parent": null, "children": [{"message_hash": "fa5535580cecd81ac814d59d52fef9cf5c11a77720a20cd123db500844f19bf9", "date": 832741850, "no_parent": null, "children": [{"message_hash": "924ea7401831bfa0f66cd68ed635eef5228ed17a79b79bb8a9977c03c814e3fc", "date": 832822935, "no_parent": null, "children": [], "subject": "Re: An alternative to remailer shutdowns", "file_year": 1996, "from": "Black Unicorn <unicorn@schloss.li>", "raw_date": "Thu, 23 May 1996 11:42:15 +0800", "to": "Andrew Loewenstern <andrew_loewenstern@il.us.swissbank.com>", "reply_to": "<9605212257.AA00853@ch1d157nwk>", "message_id": "<Pine.SUN.3.93.960522174826.15860F-100000@polaris.mindport.net>"}], "subject": "Re: An alternative to remailer shutdowns", "file_year": 1996, "from": "Andrew Loewenstern <andrew_loewenstern@il.us.swissbank.com>", "raw_date": "Wed, 22 May 1996 13:10:50 +0800", "to": "Ben Holiday <ncognito@gate.net>", "reply_to": "<Pine.A32.3.93.960521152031.52974B-100000@hopi.gate.net>", "message_id": "<9605212257.AA00853@ch1d157nwk>"}, {"message_hash": "d0c515338724d21b9913f7026cae82aec25b8ec0732f09b2f092d2986e6061df", "date": 832746950, "no_parent": null, "children": [], "subject": "Re: An alternative to remailer shutdowns", "file_year": 1996, "from": "Rich Graves <llurch@networking.stanford.edu>", "raw_date": "Wed, 22 May 1996 14:35:50 +0800", "to": "Ben Holiday <ncognito@gate.net>", "reply_to": "<Pine.A32.3.93.960521152031.52974B-100000@hopi.gate.net>", "message_id": "<Pine.GUL.3.93.960521195547.6458S-100000@Networking.Stanford.EDU>"}], "subject": "Re: An alternative to remailer shutdowns", "file_year": 1996, "from": "Ben Holiday <ncognito@gate.net>", "raw_date": "Wed, 22 May 1996 10:07:53 +0800", "to": "remailer-operators@c2.org", "reply_to": "<Pine.GUL.3.93.960520223851.489X-100000@Networking.Stanford.EDU>", "message_id": "<Pine.A32.3.93.960521152031.52974B-100000@hopi.gate.net>"}], "subject": "Re: An alternative to remailer shutdowns", "file_year": 1996, "from": "Rich Graves <llurch@networking.stanford.edu>", "raw_date": "Tue, 21 May 1996 19:28:21 +0800", "to": "cypherpunks@toad.com", "reply_to": "<0lcIFJS00YUzEZ8AMk@andrew.cmu.edu>", "message_id": "<Pine.GUL.3.93.960520223851.489X-100000@Networking.Stanford.EDU>"}, {"message_hash": "6a8df37085890c7a9f6cc821023581e30eea0d09c58aee5db330ebaad47ca06c", "date": 832745628, "no_parent": 1, "children": [{"message_hash": "588890d598da651db921761b5f27bfa842ed64ec22eb6b6eadef64cf4518e72f", "date": 832763740, "no_parent": null, "children": [], "subject": "Cutting down remailer abuse [ Was Re: An alternative ... ]", "file_year": 1996, "from": "Mike Fletcher <fletch@ain.bls.com>", "raw_date": "Wed, 22 May 1996 19:15:40 +0800", "to": "cypherpunks@toad.com", "reply_to": "<Pine.A32.3.93.960521183731.12238A-100000@seminole.gate.net>", "message_id": "<9605220533.AA14419@outland.ain_dev>"}, {"message_hash": "95dfed1702fa57b021f3fdf28484780b17aed69fd7bbcd030c33a5b32c6bc622", "date": 832822276, "no_parent": null, "children": [], "subject": "Re: An alternative to remailer shutdowns", "file_year": 1996, "from": "Black Unicorn <unicorn@schloss.li>", "raw_date": "Thu, 23 May 1996 11:31:16 +0800", "to": "Ben Holiday <ncognito@gate.net>", "reply_to": "<Pine.A32.3.93.960521183731.12238A-100000@seminole.gate.net>", "message_id": "<Pine.SUN.3.93.960522171315.15860C-100000@polaris.mindport.net>"}], "subject": "Re: An alternative to remailer shutdowns", "file_year": 1996, "from": "Ben Holiday <ncognito@gate.net>", "raw_date": "Wed, 22 May 1996 14:13:48 +0800", "to": "\"Daniel R. Oelke\" <droelke@rdxsunhost.aud.alcatel.com>", "reply_to": "<9605212219.AA05501@spirit.aud.alcatel.com>", "message_id": "<Pine.A32.3.93.960521183731.12238A-100000@seminole.gate.net>"}, {"message_hash": "7302c49ffeb412138c7c1499bd4504f329705b0f4aec9df36055ef50407b80f5", "date": 832746208, "no_parent": null, "children": [{"message_hash": "02a4d15a5f6dea383370332a2f846551b99879a7e83b58cf951b140249771b35", "date": 832749559, "no_parent": null, "children": [], "subject": "Re: The Twilight of the Remailers?", "file_year": 1996, "from": "Ben Holiday <ncognito@gate.net>", "raw_date": "Wed, 22 May 1996 15:19:19 +0800", "to": "\"Timothy C. May\" <tcmay@got.net>", "reply_to": "<adc79abe26021004b7e9@[205.199.118.202]>", "message_id": "<Pine.A32.3.93.960521231819.18798A-100000@hopi.gate.net>"}, {"message_hash": "659c68ed84542a7f658e36836af2f86c4027d865dd9b43ba9b2698197d12bdda", "date": 832754945, "no_parent": null, "children": [{"message_hash": "bdffba24268e09e509f9d7918b7411b6298fadd5cffe484448c2a582f0c9601a", "date": 832832670, "no_parent": null, "children": [{"message_hash": "7504a8cb1182af3d65f9ea788494cf16e1cad3a1ffe922c4bb1abba84998f6d6", "date": 832818844, "no_parent": null, "children": [{"message_hash": "eb28b58f47fd50a374b781e326305a3b0041a4fca28fb5571914578d8d9f093c", "date": 832896302, "no_parent": null, "children": [], "subject": "Re: The Twilight of the Remailers?", "file_year": 1996, "from": "Andrew Loewenstern <andrew_loewenstern@il.us.swissbank.com>", "raw_date": "Fri, 24 May 1996 08:05:02 +0800", "to": "mpd@netcom.com (Mike Duvos)", "reply_to": "<199605222008.NAA02211@netcom16.netcom.com>", "message_id": "<9605231751.AA00362@ch1d157nwk>"}], "subject": "Re: The Twilight of the Remailers?", "file_year": 1996, "from": "mpd@netcom.com (Mike Duvos)", "raw_date": "Thu, 23 May 1996 10:34:04 +0800", "to": "cypherpunks@toad.com", "reply_to": "<9605221917.AA00675@nwk2_ocalsl>", "message_id": "<199605222008.NAA02211@netcom16.netcom.com>"}], "subject": "Re: The Twilight of the Remailers?", "file_year": 1996, "from": "Andrew Loewenstern <andrew_loewenstern@il.us.swissbank.com>", "raw_date": "Thu, 23 May 1996 14:24:30 +0800", "to": "mpd@netcom.com (Mike Duvos)", "reply_to": "<199605220316.UAA18744@netcom2.netcom.com>", "message_id": "<9605221917.AA00675@nwk2_ocalsl>"}], "subject": "Re: The Twilight of the Remailers?", "file_year": 1996, "from": "mpd@netcom.com (Mike Duvos)", "raw_date": "Wed, 22 May 1996 16:49:05 +0800", "to": "cypherpunks@toad.com", "reply_to": "<adc79abe26021004b7e9@[205.199.118.202]>", "message_id": "<199605220316.UAA18744@netcom2.netcom.com>"}], "subject": "The Twilight of the Remailers?", "file_year": 1996, "from": "tcmay@got.net (Timothy C. May)", "raw_date": "Wed, 22 May 1996 14:23:28 +0800", "to": "cypherpunks@toad.com", "reply_to": null, "message_id": "<adc79abe26021004b7e9@[205.199.118.202]>"}, {"message_hash": "fdced01693efee2e7c64ccde47d7e7929aa15b3a321de53bdcaede3ca1fe2761", "date": 833151165, "no_parent": 1, "children": [{"message_hash": "fb4e4496ac767e140ccca6520d9b52c267314da849b84e56aff71b674229e3ab", "date": 833160791, "no_parent": null, "children": [{"message_hash": "d53e4d33d1fa53dacaa00e9dbfb3568081575662b25e59830982b538af8b49e1", "date": 833183816, "no_parent": null, "children": [], "subject": "Re: nCognito is Dead..", "file_year": 1996, "from": "Rich Graves <llurch@networking.stanford.edu>", "raw_date": "Mon, 27 May 1996 15:56:56 +0800", "to": "cypherpunks@toad.com", "reply_to": "<Pine.LNX.3.93.960526182121.413B-100000@gak>", "message_id": "<Pine.GUL.3.93.960526215524.10152G-100000@Networking.Stanford.EDU>"}], "subject": "Re: nCognito is Dead..", "file_year": 1996, "from": "\"Mark M.\" <markm@voicenet.com>", "raw_date": "Mon, 27 May 1996 09:33:11 +0800", "to": "Ben Holiday <ncognito@gate.net>", "reply_to": "<Pine.A32.3.93.960525155235.39848B-100000@navajo.gate.net>", "message_id": "<Pine.LNX.3.93.960526182121.413B-100000@gak>"}], "subject": "nCognito is Dead..", "file_year": 1996, "from": "Ben Holiday <ncognito@gate.net>", "raw_date": "Mon, 27 May 1996 06:52:45 +0800", "to": "cypherpunks@toad.com", "reply_to": "<Pine.NEB.3.93.960525061231.6707C-100000@alpha.jpunix.com>", "message_id": "<Pine.A32.3.93.960525155235.39848B-100000@navajo.gate.net>"}, {"message_hash": "4475d75f00d0be88e128149133033f234cd92854821d51e3b8225af64f43d904", "date": 833262473, "no_parent": null, "children": [{"message_hash": "904616de3de1e6cbe73f89256c30033a0cf76c43c41f3d91e1c6da8f694adc58", "date": 833264482, "no_parent": null, "children": [{"message_hash": "05c9caac47f8db2e8425d59fc15f515fbe1279421909e2bbd67d1834bb93473d", "date": 833260306, "no_parent": null, "children": [], "subject": "Re: Asendmail For Mix [Testers Needed]", "file_year": 1996, "from": "Ben Holiday <ncognito@gate.net>", "raw_date": "Tue, 28 May 1996 13:11:46 +0800", "to": "\"John A. Perry\" <perry@alpha.jpunix.com>", "reply_to": "<Pine.NEB.3.93.960527202333.27433A-100000@alpha.jpunix.com>", "message_id": "<Pine.A32.3.93.960527213325.55980A-100000@hopi.gate.net>"}], "subject": "Re: Asendmail For Mix [Testers Needed]", "file_year": 1996, "from": "\"John A. Perry\" <perry@alpha.jpunix.com>", "raw_date": "Tue, 28 May 1996 14:21:22 +0800", "to": "Ben Holiday <ncognito@gate.net>", "reply_to": "<Pine.A32.3.93.960527204713.60624A-100000@hopi.gate.net>", "message_id": "<Pine.NEB.3.93.960527202333.27433A-100000@alpha.jpunix.com>"}], "subject": "Asendmail For Mix [Testers Needed]", "file_year": 1996, "from": "Ben Holiday <ncognito@gate.net>", "raw_date": "Tue, 28 May 1996 13:47:53 +0800", "to": "remailer-operators@c2.org", "reply_to": null, "message_id": "<Pine.A32.3.93.960527204713.60624A-100000@hopi.gate.net>"}, {"message_hash": "a05a5f3eb50875d90a939b286aa996bee145cb3329966ad362f1d6fc88da6231", "date": 833439069, "no_parent": null, "children": [], "subject": "Asendmail Status & Politikal Rant", "file_year": 1996, "from": "Ben Holiday <ncognito@gate.net>", "raw_date": "Thu, 30 May 1996 14:51:09 +0800", "to": "remailer-operators@c2.org", "reply_to": null, "message_id": "<Pine.A32.3.93.960529211352.30940A-100000@seminole.gate.net>"}, {"message_hash": "3d3ef67a38dfcb9c0d5cf0315678ffa6cd8f6462152aff3d10986aef61bb5639", "date": 833599324, "no_parent": null, "children": [], "subject": "Asendmail V0.5beta is available now.", "file_year": 1996, "from": "Ben Holiday <ncognito@gate.net>", "raw_date": "Sat, 1 Jun 1996 11:22:04 +0800", "to": "cypherpunks@toad.com", "reply_to": null, "message_id": "<Pine.A32.3.93.960531185723.54098A-100000@navajo.gate.net>"}, {"message_hash": "455030782294f6a87e8396c6366047d2596afb04dbf1de33728c3fde7217ff5d", "date": 833922800, "no_parent": null, "children": [], "subject": "Asendmail v0.5beta", "file_year": 1996, "from": "Ben Holiday <ncognito@gate.net>", "raw_date": "Wed, 5 Jun 1996 05:13:20 +0800", "to": "remailer-operators@c2.org", "reply_to": null, "message_id": "<Pine.A32.3.93.960603181502.59148A-100000@hopi.gate.net>"}, {"message_hash": "2a2e6f2f9087a63244b9cf4d2679ebdc33a84cfbd40d1cf069f9109a6b3e380f", "date": 833924276, "no_parent": null, "children": [{"message_hash": "9bb49da242928b3befc674e0f21000676c9acf49f3d2c47d06bd3881863657ce", "date": 833934472, "no_parent": null, "children": [], "subject": "Re: Electronic Signature Act Of 1996", "file_year": 1996, "from": "\"Perry E. Metzger\" <perry@piermont.com>", "raw_date": "Wed, 5 Jun 1996 08:27:52 +0800", "to": "Ben Holiday <ncognito@gate.net>", "reply_to": "<Pine.A32.3.93.960604102759.21416A-100000@navajo.gate.net>", "message_id": "<199606041511.LAA09110@jekyll.piermont.com>"}], "subject": "Electronic Signature Act Of 1996", "file_year": 1996, "from": "Ben Holiday <ncognito@gate.net>", "raw_date": "Wed, 5 Jun 1996 05:37:56 +0800", "to": "cypherpunks@toad.com", "reply_to": null, "message_id": "<Pine.A32.3.93.960604102759.21416A-100000@navajo.gate.net>"}, {"message_hash": "b30aea5fec475d0e404b7d7a259e884a270f5da29a182fd6216b3896db0914cb", "date": 833938586, "no_parent": null, "children": [], "subject": "Asendmail yet again", "file_year": 1996, "from": "Ben Holiday <ncognito@gate.net>", "raw_date": "Wed, 5 Jun 1996 09:36:26 +0800", "to": "cypherpunks@toad.com", "reply_to": null, "message_id": "<Pine.A32.3.93.960604131256.53274A-100000@seminole.gate.net>"}, {"message_hash": "c385fe2d68de5de80b3f62e63ce683e45cb4f7c0f049292dc3c39a3aea3ebf1c", "date": 833943230, "no_parent": null, "children": [{"message_hash": "f2652ed2d4dde98fd97338b676bcd603a708cfe1aaa92f3dbead9c04436e5f97", "date": 833965598, "no_parent": null, "children": [{"message_hash": "9d5505f03e361998f16b2b9470dca9ef6aec5bfbafc3bdb0d5be6590079d2faa", "date": 833994055, "no_parent": null, "children": [], "subject": "Re: How to explain crypto?", "file_year": 1996, "from": "\"Perry E. Metzger\" <perry@piermont.com>", "raw_date": "Thu, 6 Jun 1996 01:00:55 +0800", "to": "Ben Holiday <ncognito@gate.net>", "reply_to": "<Pine.A32.3.93.960604185950.36410A-100000@seminole.gate.net>", "message_id": "<199606051224.IAA11983@jekyll.piermont.com>"}], "subject": "Re: How to explain crypto?", "file_year": 1996, "from": "Ben Holiday <ncognito@gate.net>", "raw_date": "Wed, 5 Jun 1996 17:06:38 +0800", "to": "Declan McCullagh <declan@well.com>", "reply_to": "<v01510100adda3101165c@[204.62.128.229]>", "message_id": "<Pine.A32.3.93.960604185950.36410A-100000@seminole.gate.net>"}], "subject": "How to explain crypto?", "file_year": 1996, "from": "declan@well.com (Declan McCullagh)", "raw_date": "Wed, 5 Jun 1996 10:53:50 +0800", "to": "cypherpunks@toad.com", "reply_to": null, "message_id": "<v01510100adda3101165c@[204.62.128.229]>"}, {"message_hash": "f57abd6ff769dc032be7e0a6291e8fda2f71637a254cf228ac6efaf51ca0bdce", "date": 836692763, "no_parent": null, "children": [{"message_hash": "4a77d9f40559ba575dbce5cd48d7f1c6d5916f2760ce6ee58f5e71c23206c557", "date": 836862137, "no_parent": null, "children": [{"message_hash": "bb8803b63d29923680695758066a7365641f86989544c55fe70dcb7c2d3a7e1f", "date": 836878921, "no_parent": null, "children": [{"message_hash": "f28ac3873478bf0e8675f3003a7515c952b29712f2b9aca82614cbbfb0554077", "date": 836893941, "no_parent": null, "children": [{"message_hash": "52a4420afa4f0d488b2a4c938794f051b57e79bf9b930df3908776b00a53c0e9", "date": 836899696, "no_parent": null, "children": [{"message_hash": "a64851587d78fae752fa7578550fed6b931caa947b682e2b480f5164a704e5a0", "date": 836967579, "no_parent": null, "children": [], "subject": "Re: Word lists for passphrases [vocabularypunks]", "file_year": 1996, "from": "Steven L Baur <steve@miranova.com>", "raw_date": "Wed, 10 Jul 1996 10:59:39 +0800", "to": "\"Mark M.\" <markm@voicenet.com>", "reply_to": "<Pine.LNX.3.94.960709010857.1246B-100000@gak>", "message_id": "<m2spb1b2py.fsf@deanna.miranova.com>"}], "subject": "Re: Word lists for passphrases", "file_year": 1996, "from": "\"Mark M.\" <markm@voicenet.com>", "raw_date": "Tue, 9 Jul 1996 16:08:16 +0800", "to": "\"Igor Chudov @ home\" <ichudov@algebra.com>", "reply_to": "<199607090210.VAA07394@manifold.algebra.com>", "message_id": "<Pine.LNX.3.94.960709010857.1246B-100000@gak>"}], "subject": "Re: Word lists for passphrases", "file_year": 1996, "from": "ichudov@algebra.com (Igor Chudov @ home)", "raw_date": "Tue, 9 Jul 1996 14:32:21 +0800", "to": "ncognito@gate.net (Ben Holiday)", "reply_to": "<Pine.A32.3.93.960708174618.18872A-100000@navajo.gate.net>", "message_id": "<199607090210.VAA07394@manifold.algebra.com>"}], "subject": "Re: Word lists for passphrases", "file_year": 1996, "from": "Ben Holiday <ncognito@gate.net>", "raw_date": "Tue, 9 Jul 1996 10:22:01 +0800", "to": "cypherpunks@toad.com", "reply_to": "<199607081635.MAA10394@jekyll.piermont.com>", "message_id": "<Pine.A32.3.93.960708174618.18872A-100000@navajo.gate.net>"}], "subject": "Re: Word lists for passphrases", "file_year": 1996, "from": "\"Perry E. Metzger\" <perry@piermont.com>", "raw_date": "Tue, 9 Jul 1996 05:42:17 +0800", "to": "AwakenToMe@aol.com", "reply_to": "<960706155139_428652398@emout15.mail.aol.com>", "message_id": "<199607081635.MAA10394@jekyll.piermont.com>"}], "subject": "Re: Word lists for passphrases", "file_year": 1996, "from": "AwakenToMe@aol.com", "raw_date": "Sun, 7 Jul 1996 06:39:23 +0800", "to": "cypherpunks@toad.com", "reply_to": null, "message_id": "<960706155139_428652398@emout15.mail.aol.com>"}, {"message_hash": "4cb5400b9e9c5ab2fe404067f302a5c7a59d7199f80948512a4f5722c05ab667", "date": 838059236, "no_parent": null, "children": [{"message_hash": "73fad6f02c763a44630bf584bacf633a1a1c7c90996fdde5ce73f144e0c9dab6", "date": 838082971, "no_parent": null, "children": [{"message_hash": "4bd11d2add874007e1b19fd4c51c1bacce2ede7397e552a0a0d01f50f5e68d92", "date": 838090624, "no_parent": null, "children": [{"message_hash": "98ca41831d7e928e0a6654c20c64bf542326adf45187d0bb0b6dd9747870f9f0", "date": 838110560, "no_parent": null, "children": [{"message_hash": "d4a68fed53a3301b0e0eab28005e5aa2882824a41b5d13e66d03809a0bfdee6b", "date": 838086669, "no_parent": null, "children": [{"message_hash": "3bb799530c334fed89f3ccc5490408b5dc75a223b28922e0449c8170b3c8f440", "date": 838178694, "no_parent": null, "children": [], "subject": "Re: Distributed DES crack", "file_year": 1996, "from": "The Deviant <deviant@pooh-corner.com>", "raw_date": "Wed, 24 Jul 1996 11:24:54 +0800", "to": "\"Perry E. Metzger\" <perry@piermont.com>", "reply_to": "<199607222314.TAA12858@jekyll.piermont.com>", "message_id": "<Pine.LNX.3.94.960723174600.973A-100000@switch.sp.org>"}, {"message_hash": "68dbf7d9da4bdecc6208e92ef69e1614a6a15f06c57f4be4b9be02b30b7bc557", "date": 838209668, "no_parent": null, "children": [], "subject": "Re: Distributed DES crack", "file_year": 1996, "from": "Simon Spero <ses@tipper.oit.unc.edu>", "raw_date": "Wed, 24 Jul 1996 20:01:08 +0800", "to": "\"Perry E. Metzger\" <perry@piermont.com>", "reply_to": "<199607222314.TAA12858@jekyll.piermont.com>", "message_id": "<Pine.SUN.3.91.960723093316.28197A@tipper.oit.unc.edu>"}], "subject": "Re: Distributed DES crack", "file_year": 1996, "from": "\"Perry E. Metzger\" <perry@piermont.com>", "raw_date": "Tue, 23 Jul 1996 09:51:09 +0800", "to": "Ben Holiday <ncognito@gate.net>", "reply_to": "<Pine.A32.3.93.960722174148.48340B-100000@navajo.gate.net>", "message_id": "<199607222314.TAA12858@jekyll.piermont.com>"}, {"message_hash": "c9d0c58bd210ace1dc72207db12617a34f8c329302d693e3c86c7138a17d81a7", "date": 838125080, "no_parent": null, "children": [{"message_hash": "c6b5a25eeb8adf296f70b802f741acddf0efb6010e398a3f04cc49ceb2bb0e2a", "date": 838143133, "no_parent": null, "children": [], "subject": "Re: Distributed DES crack", "file_year": 1996, "from": "=?ISO-8859-1?Q?J=FCri_Kaljundi?= <jk@stallion.ee>", "raw_date": "Wed, 24 Jul 1996 01:32:13 +0800", "to": "cypherpunks@toad.com", "reply_to": "<199607230422.AAA09435@crypto.com>", "message_id": "<Pine.GSO.3.93.960723162113.9199D-100000@nebula.online.ee>"}, {"message_hash": "8962e71b3704c2983975342474ad6870ce1011fd3623d600adb2a6207b6e1984", "date": 838176617, "no_parent": null, "children": [{"message_hash": "b0bdaf662b4690152192bd481b87e3951fb71f70f1aa9e8517a501fa3c4fb20a", "date": 838172465, "no_parent": null, "children": [{"message_hash": "0c921213efa1f62c46a2f6ebc6fa4bd42f459fa5e6a759081e118839a5ae0975", "date": 838185756, "no_parent": null, "children": [], "subject": "Re: Distributed DES crack", "file_year": 1996, "from": "Roger Williams <roger@coelacanth.com>", "raw_date": "Wed, 24 Jul 1996 13:22:36 +0800", "to": "Matt Blaze <mab@crypto.com>", "reply_to": "<199607231430.KAA14775@crypto.com>", "message_id": "<rogerg26ipah8.fsf@sturgeon.coelacanth.com>"}], "subject": "Re: Distributed DES crack", "file_year": 1996, "from": "Matt Blaze <mab@crypto.com>", "raw_date": "Wed, 24 Jul 1996 09:41:05 +0800", "to": "\"Mark O. Aldrich\" <maldrich@grci.com>", "reply_to": "<Pine.SCO.3.93.960723093328.11859A-100000@grctechs.va.grci.com>", "message_id": "<199607231430.KAA14775@crypto.com>"}], "subject": "Re: Distributed DES crack", "file_year": 1996, "from": "\"Mark O. Aldrich\" <maldrich@grci.com>", "raw_date": "Wed, 24 Jul 1996 10:50:17 +0800", "to": "Matt Blaze <mab@crypto.com>", "reply_to": "<199607230422.AAA09435@crypto.com>", "message_id": "<Pine.SCO.3.93.960723093328.11859A-100000@grctechs.va.grci.com>"}, {"message_hash": "3e59475447c95dfc8c61d1ceee6cb5e81def97d74a6878b6dd36beccccd7bf09", "date": 838200875, "no_parent": null, "children": [{"message_hash": "b800be96532b18ae79f5615843671eca534b8d424204d2089fb0772e2df0376a", "date": 838166766, "no_parent": null, "children": [{"message_hash": "d9d694be00094931b4473c59713131a49112fce7e7dc65942a35eaf3926f4a35", "date": 838153416, "no_parent": null, "children": [], "subject": "Re: Distributed DES crack", "file_year": 1996, "from": "\"Perry E. Metzger\" <perry@piermont.com>", "raw_date": "Wed, 24 Jul 1996 04:23:36 +0800", "to": "Matt Blaze <mab@crypto.com>", "reply_to": "<199607231412.KAA14573@crypto.com>", "message_id": "<199607231419.KAA15900@jekyll.piermont.com>"}], "subject": "Re: Distributed DES crack", "file_year": 1996, "from": "Matt Blaze <mab@crypto.com>", "raw_date": "Wed, 24 Jul 1996 08:06:06 +0800", "to": "perry@piermont.com", "reply_to": "<199607231331.JAA15803@jekyll.piermont.com>", "message_id": "<199607231412.KAA14573@crypto.com>"}], "subject": "Re: Distributed DES crack", "file_year": 1996, "from": "\"Perry E. Metzger\" <perry@piermont.com>", "raw_date": "Wed, 24 Jul 1996 17:34:35 +0800", "to": "Matt Blaze <mab@crypto.com>", "reply_to": "<199607230422.AAA09435@crypto.com>", "message_id": "<199607231331.JAA15803@jekyll.piermont.com>"}], "subject": "Re: Distributed DES crack", "file_year": 1996, "from": "Matt Blaze <mab@crypto.com>", "raw_date": "Tue, 23 Jul 1996 20:31:20 +0800", "to": "cypherpunks@toad.com", "reply_to": "<Pine.A32.3.93.960722174148.48340B-100000@navajo.gate.net>", "message_id": "<199607230422.AAA09435@crypto.com>"}], "subject": "Distributed DES crack", "file_year": 1996, "from": "Ben Holiday <ncognito@gate.net>", "raw_date": "Tue, 23 Jul 1996 16:29:20 +0800", "to": "\"Perry E. Metzger\" <perry@piermont.com>", "reply_to": "<199607221830.OAA12526@jekyll.piermont.com>", "message_id": "<Pine.A32.3.93.960722174148.48340B-100000@navajo.gate.net>"}], "subject": "Re: Borders *are* transparent", "file_year": 1996, "from": "\"Perry E. Metzger\" <perry@piermont.com>", "raw_date": "Tue, 23 Jul 1996 10:57:04 +0800", "to": "cypherpunks@toad.com", "reply_to": "<199607221650.EAA01429@mycroft.actrix.gen.nz>", "message_id": "<199607221830.OAA12526@jekyll.piermont.com>"}], "subject": "Re: Borders *are* transparent", "file_year": 1996, "from": "Paul Foley <paul@mycroft.actrix.gen.nz>", "raw_date": "Tue, 23 Jul 1996 08:49:31 +0800", "to": "trei@process.com", "reply_to": "<199607221420.HAA00786@toad.com>", "message_id": "<199607221650.EAA01429@mycroft.actrix.gen.nz>"}, {"message_hash": "f42dfba40d96bc464b11e0bb2d0e88524ca902d2e39dfb9d8261a46cfbe610c1", "date": 838122189, "no_parent": null, "children": [{"message_hash": "bfb5525bff5e22a1b7588a8f416b36b703b8257627d85cf645ed3d714411426a", "date": 838152185, "no_parent": null, "children": [{"message_hash": "9e6359d394dad6656e1c16a3fb02050fc68d4ad05b3dcb9365ffca4fa7df378f", "date": 838168103, "no_parent": null, "children": [{"message_hash": "dd00381dcfdb1806f804f090129a649c3221d8ec5df3dccfa501c0c1dd74c56b", "date": 838205785, "no_parent": null, "children": [], "subject": "Re: Borders *are* transparent", "file_year": 1996, "from": "The Deviant <deviant@pooh-corner.com>", "raw_date": "Wed, 24 Jul 1996 18:56:25 +0800", "to": "Simon Spero <ses@tipper.oit.unc.edu>", "reply_to": "<Pine.SUN.3.91.960723132622.28907A-100000@tipper.oit.unc.edu>", "message_id": "<Pine.LNX.3.94.960724072354.1558C-100000@switch.sp.org>"}], "subject": "Re: Borders *are* transparent", "file_year": 1996, "from": "Simon Spero <ses@tipper.oit.unc.edu>", "raw_date": "Wed, 24 Jul 1996 08:28:23 +0800", "to": "\"Peter D. Junger\" <junger@pdj2-ra.F-REMOTE.CWRU.Edu>", "reply_to": "<199607231437.KAA20409@pdj2-ra.F-REMOTE.CWRU.Edu>", "message_id": "<Pine.SUN.3.91.960723132622.28907A-100000@tipper.oit.unc.edu>"}], "subject": "Re: Borders *are* transparent", "file_year": 1996, "from": "\"Peter D. Junger\" <junger@pdj2-ra.F-REMOTE.CWRU.Edu>", "raw_date": "Wed, 24 Jul 1996 04:03:05 +0800", "to": "Cypherpunks <cypherpunks@toad.com>", "reply_to": "<v03007803ae1a08ca5dc1@[207.67.246.99]>", "message_id": "<199607231437.KAA20409@pdj2-ra.F-REMOTE.CWRU.Edu>"}], "subject": "Re: Borders *are* transparent", "file_year": 1996, "from": "Marshall Clow <mclow@owl.csusm.edu>", "raw_date": "Tue, 23 Jul 1996 19:43:09 +0800", "to": "cypherpunks@toad.com", "reply_to": "<199607221420.HAA00786@toad.com>", "message_id": "<v03007803ae1a08ca5dc1@[207.67.246.99]>"}], "subject": "Re: Borders *are* transparent", "file_year": 1996, "from": "\"Peter Trei\" <trei@process.com>", "raw_date": "Tue, 23 Jul 1996 02:13:56 +0800", "to": "trei@process.com", "reply_to": null, "message_id": "<199607221420.HAA00786@toad.com>"}, {"message_hash": "eb0897b512cedcd5cb9ab1efd990de012c41f9d44e02dffcdbab22309a448171", "date": 841107522, "no_parent": null, "children": [{"message_hash": "a1abcc4cb9320025decc6aeee857e7b53293c8b9e516fc010ee1e768de88ff68", "date": 841118910, "no_parent": null, "children": [], "subject": "Re: Microsoft Explorer security hole (fwd)", "file_year": 1996, "from": "ichudov@algebra.com (Igor Chudov @ home)", "raw_date": "Tue, 27 Aug 1996 12:08:30 +0800", "to": "ncognito@gate.net (Ben Holiday)", "reply_to": "<Pine.A32.3.93.960826001930.31882A-100000@seminole.gate.net>", "message_id": "<199608262206.RAA03891@manifold.algebra.com>"}], "subject": "Microsoft Explorer security hole (fwd)", "file_year": 1996, "from": "Ben Holiday <ncognito@gate.net>", "raw_date": "Tue, 27 Aug 1996 08:58:42 +0800", "to": "cypherpunks@toad.com", "reply_to": null, "message_id": "<Pine.A32.3.93.960826001930.31882A-100000@seminole.gate.net>"}], "sender_id": "ben_holiday_ncognito_at_gate_net_"}