{"count": 5, "from": "cg@bofh.lake.de (Cees de Groot)", "threads": [{"message_hash": "4472e1cc962bd7499d6639f7b680a54b6e8ff452e6beecaae0017530c23fa0f4", "date": 809239722, "no_parent": null, "children": [{"message_hash": "683ca7e99b3fc83a599e12a8d99f33915a6c8182f1a21dfa8dddbfc03029aa74", "date": 809243083, "no_parent": null, "children": [{"message_hash": "9e8664d755db9ee4317205f66c301e0d83e294451cbe22e93b483b49ab4b019d", "date": 809247061, "no_parent": null, "children": [{"message_hash": "717bc62c15b73a026582434cfae4809f0580667130882e96ebaded587e55ce43", "date": 809250868, "no_parent": null, "children": [], "subject": "Re: Linux brutessl client", "file_year": 1995, "from": "zinc <zinc@zifi.genetics.utah.edu>", "raw_date": "Thu, 24 Aug 95 00:54:28 PDT", "to": "Piete Brooks <Piete.Brooks@cl.cam.ac.uk>", "reply_to": "<\"swan.cl.cam.:164680:950824065040\"@cl.cam.ac.uk>", "message_id": "<Pine.LNX.3.91.950824015247.452A-100000@zifi.genetics.utah.edu>"}], "subject": "Re: Linux brutessl client", "file_year": 1995, "from": "Piete Brooks <Piete.Brooks@cl.cam.ac.uk>", "raw_date": "Wed, 23 Aug 95 23:51:01 PDT", "to": "zinc <zinc@zifi.genetics.utah.edu>", "reply_to": "<Pine.LNX.3.91.950823233650.3783J-100000@zifi.genetics.utah.edu>", "message_id": "<\"swan.cl.cam.:164680:950824065040\"@cl.cam.ac.uk>"}], "subject": "Re: Linux brutessl client", "file_year": 1995, "from": "zinc <zinc@zifi.genetics.utah.edu>", "raw_date": "Wed, 23 Aug 95 22:44:43 PDT", "to": "Sam Quigley <poodge@econ.Berkeley.EDU>", "reply_to": "<199508240448.VAA12304@quesnay.Berkeley.EDU>", "message_id": "<Pine.LNX.3.91.950823233650.3783J-100000@zifi.genetics.utah.edu>"}, {"message_hash": "26d38da3c37b784f76df7da4ad147c4295c58983d700911a36242e27ff7fa90a", "date": 809265268, "no_parent": null, "children": [], "subject": "Re: Linux brutessl client", "file_year": 1995, "from": "cg@bofh.lake.de (Cees de Groot)", "raw_date": "Thu, 24 Aug 95 04:54:28 PDT", "to": "poodge@econ.Berkeley.EDU (Sam Quigley)", "reply_to": "<199508240448.VAA12304@quesnay.Berkeley.EDU>", "message_id": "<m0slaeI-000PZbC@bofh.lake.de>"}], "subject": "Linux brutessl client", "file_year": 1995, "from": "Sam Quigley <poodge@econ.Berkeley.EDU>", "raw_date": "Wed, 23 Aug 95 21:48:42 PDT", "to": "cypherpunks@toad.com", "reply_to": null, "message_id": "<199508240448.VAA12304@quesnay.Berkeley.EDU>"}, {"message_hash": "40dd55c1562238de9256dd476640e9c89f87254c7e69dff155d718c151762923", "date": 809309736, "no_parent": null, "children": [{"message_hash": "3969b9ee8bcbebe78922a193386b361a0a680d4cffca3275cfcb22eb211dce67", "date": 809312385, "no_parent": null, "children": [{"message_hash": "f3bba42d03421e26f96d4136614157f05a437df668f5df6c068087b3cbd27841", "date": 809349119, "no_parent": null, "children": [{"message_hash": "8ad52094c7bcf0d81c30e7f9fe5d7e2907df052b99952fc0b06eafa90336c74b", "date": 809351144, "no_parent": null, "children": [{"message_hash": "f77a53f29d8e63c74507f87d01740372ba4fbc54e8e0ccf5bb41b8ba42576384", "date": 809352275, "no_parent": null, "children": [], "subject": "Re: improving the distributed computation", "file_year": 1995, "from": "Piete Brooks <Piete.Brooks@cl.cam.ac.uk>", "raw_date": "Fri, 25 Aug 95 05:04:35 PDT", "to": "fc@all.net (Dr. Frederick B. Cohen)", "reply_to": "<9508251143.AA15702@all.net>", "message_id": "<\"swan.cl.cam.:252910:950825120349\"@cl.cam.ac.uk>"}, {"message_hash": "37952c735c6479c1cceee1f7b68bfa272830c834f57f2de2b6a582a09a8ad7c0", "date": 809369538, "no_parent": null, "children": [], "subject": "Re: improving the distributed computation", "file_year": 1995, "from": "cg@bofh.lake.de (Cees de Groot)", "raw_date": "Fri, 25 Aug 95 09:52:18 PDT", "to": "fc@all.net (Dr. Frederick B. Cohen)", "reply_to": "<9508251143.AA15702@all.net>", "message_id": "<m0sm205-000PZjC@bofh.lake.de>"}], "subject": "improving the distributed computation", "file_year": 1995, "from": "fc@all.net (Dr. Frederick B. Cohen)", "raw_date": "Fri, 25 Aug 95 04:45:44 PDT", "to": "Piete.Brooks@cl.cam.ac.uk (Piete Brooks)", "reply_to": "<\"swan.cl.cam.:226410:950825111043\"@cl.cam.ac.uk>", "message_id": "<9508251143.AA15702@all.net>"}, {"message_hash": "22b92ab6cbb126e770b4ffc2ad99204cae363182e349a2ecdd7fb8e296e4603f", "date": 809383342, "no_parent": null, "children": [{"message_hash": "a907e6bbba27abca4a84aaccee6cde7012fa3702a8f6984ccee6625cb68f79ab", "date": 809387549, "no_parent": null, "children": [], "subject": "Re: Cypherpunk Brute Squad [Re: SSL Challenge: Server problems]", "file_year": 1995, "from": "Piete Brooks <Piete.Brooks@cl.cam.ac.uk>", "raw_date": "Fri, 25 Aug 95 14:52:29 PDT", "to": "\"J. R. Valverde (EMBL Outstation: the EBI)\" <txomsy@ebi.ac.uk>", "reply_to": "<199508252041.VAA01686@neptune.ebi.ac.uk>", "message_id": "<\"swan.cl.cam.:196070:950825215208\"@cl.cam.ac.uk>"}], "subject": "Re: Cypherpunk Brute Squad [Re: SSL Challenge: Server problems]", "file_year": 1995, "from": "\"J. R. Valverde (EMBL Outstation: the EBI)\" <txomsy@ebi.ac.uk>", "raw_date": "Fri, 25 Aug 95 13:42:22 PDT", "to": "cypherpunks@toad.com", "reply_to": "<\"swan.cl.cam.:226410:950825111043\"@cl.cam.ac.uk>", "message_id": "<199508252041.VAA01686@neptune.ebi.ac.uk>"}], "subject": "Re: Cypherpunk Brute Squad [Re: SSL Challenge: Server problems]", "file_year": 1995, "from": "Piete Brooks <Piete.Brooks@cl.cam.ac.uk>", "raw_date": "Fri, 25 Aug 95 04:11:59 PDT", "to": "jim@acm.org", "reply_to": "<199508250059.RAA02668@mycroft.rand.org>", "message_id": "<\"swan.cl.cam.:226410:950825111043\"@cl.cam.ac.uk>"}], "subject": "Cypherpunk Brute Squad [Re: SSL Challenge: Server problems]", "file_year": 1995, "from": "Jim Gillogly <jim@acm.org>", "raw_date": "Thu, 24 Aug 95 17:59:45 PDT", "to": "cypherpunks@toad.com", "reply_to": "<9508250015.AA22053@toad.com>", "message_id": "<199508250059.RAA02668@mycroft.rand.org>"}, {"message_hash": "6e3b0ee894c6aace9d154338af13909f9e8cd4e889fca02709fcf8f86be34370", "date": 809312558, "no_parent": null, "children": [], "subject": "Re: SSL Challenge: Server problems", "file_year": 1995, "from": "Piete Brooks <Piete.Brooks@cl.cam.ac.uk>", "raw_date": "Thu, 24 Aug 95 18:02:38 PDT", "to": "trei@process.com", "reply_to": "<9508250015.AA22053@toad.com>", "message_id": "<\"swan.cl.cam.:020170:950825010219\"@cl.cam.ac.uk>"}], "subject": "SSL Challenge: Server problems", "file_year": 1995, "from": "\"Peter Trei\" <trei@process.com>", "raw_date": "Thu, 24 Aug 95 17:15:36 PDT", "to": "cypherpunks@toad.com", "reply_to": null, "message_id": "<9508250015.AA22053@toad.com>"}, {"message_hash": "8752e31f20efb31105fdd026d3f7dad5b922798f089df24b7e50bb775840a87e", "date": 809387724, "no_parent": null, "children": [{"message_hash": "56817b852b3d02a6ab2e57d325acaae8ccf05e1f6b757dd71be4b20793ba3ebe", "date": 809436532, "no_parent": null, "children": [{"message_hash": "0dab3f7fae6f98e6944687f8965ebf7c43e6303b4b98451f92b62dbe4852e53b", "date": 809442314, "no_parent": null, "children": [{"message_hash": "a461c7c4ff2e20d5fc82af101321fa26dadf22747b30644f2240871f9eba6375", "date": 809444942, "no_parent": null, "children": [], "subject": "Re: Wide Release (Re: PGPfone (BETA TEST) is released)", "file_year": 1995, "from": "Bob Snyder <rsnyder@janet.advsys.com>", "raw_date": "Sat, 26 Aug 95 06:49:02 PDT", "to": "cypherpunks@toad.com", "reply_to": "<m0smKvJ-000PZgC@bofh.lake.de>", "message_id": "<199508261349.JAA23170@janet.advsys.com>"}], "subject": "Re: Wide Release (Re: PGPfone (BETA TEST) is released)", "file_year": 1995, "from": "cg@bofh.lake.de (Cees de Groot)", "raw_date": "Sat, 26 Aug 95 06:05:14 PDT", "to": "rsnyder@janet.advsys.com (Bob Snyder)", "reply_to": "<199508261129.HAA22154@janet.advsys.com>", "message_id": "<m0smKvJ-000PZgC@bofh.lake.de>"}], "subject": "Re: Wide Release (Re: PGPfone (BETA TEST) is released)", "file_year": 1995, "from": "Bob Snyder <rsnyder@janet.advsys.com>", "raw_date": "Sat, 26 Aug 95 04:28:52 PDT", "to": "cypherpunks@toad.com", "reply_to": "<199508252155.XAA06116@utopia.hacktic.nl>", "message_id": "<199508261129.HAA22154@janet.advsys.com>"}], "subject": "Wide Release (Re: PGPfone (BETA TEST) is released)", "file_year": 1995, "from": "anon-remailer@utopia.hacktic.nl (Anonymous)", "raw_date": "Fri, 25 Aug 95 14:55:24 PDT", "to": "cypherpunks@toad.com", "reply_to": null, "message_id": "<199508252155.XAA06116@utopia.hacktic.nl>"}, {"message_hash": "00f1ac4afe85dd6f827fdfe0cb2209eb636c57fc7d70c4e456f636f1a1c87aed", "date": 810262073, "no_parent": null, "children": [{"message_hash": "b2bc23a629f322f37b67c98d7a20fe4b1e1ef4d1958c8e5eb2ea215b103ced88", "date": 810293858, "no_parent": null, "children": [], "subject": "Re: maximizing cryptographic return", "file_year": 1995, "from": "cg@bofh.lake.de (Cees de Groot)", "raw_date": "Tue, 5 Sep 95 02:37:38 PDT", "to": "monty.harder@famend.com", "reply_to": "<8B072A1.00030003E8.uuout@famend.com>", "message_id": "<m0spu0n-000PZnC@bofh.lake.de>"}], "subject": "maximizing cryptographic return", "file_year": 1995, "from": "monty.harder@famend.com (MONTY HARDER)", "raw_date": "Mon, 4 Sep 95 17:47:53 PDT", "to": "CYPHERPUNKS@toad.com", "reply_to": null, "message_id": "<8B072A1.00030003E8.uuout@famend.com>"}, {"message_hash": "e636946ca693ff60d7ae3f22df6df6b74c6e55c00dd469963b9abe6ee3816147", "date": 810419352, "no_parent": null, "children": [{"message_hash": "00643e4a9e098e4ce5e94221c9f24a6fe59b06658d77cdc6537c78dc2ded2eeb", "date": 810445587, "no_parent": null, "children": [{"message_hash": "5887fafaa047b93b68d441e79cdf3f6ff8a18b20a50f8c84a8fb9285e9c90c93", "date": 810453798, "no_parent": null, "children": [{"message_hash": "701a767d585ede749ad64b5e2d6ad0aebcf1584010811f0b531949b3cec57c3f", "date": 810521923, "no_parent": null, "children": [{"message_hash": "9f3033692a6c835aee05f0eab2510adf5aef07ef07710975830f6c24ed361d0d", "date": 810957559, "no_parent": null, "children": [{"message_hash": "29bf54a7481f819203327b398c073f9e74068274aae39f9041dedb355685a7ae", "date": 811132167, "no_parent": null, "children": [{"message_hash": "a4fed26c5f4fdd14564e8b534ea0a548f46488cac2148d2567c8de3ff9a941c4", "date": 811563403, "no_parent": null, "children": [], "subject": "Re: Scientology and police visit XS4ALL Amsterdam", "file_year": 1995, "from": "Jiri Baum <jirib@cs.monash.edu.au>", "raw_date": "Tue, 19 Sep 95 19:16:43 PDT", "to": "starrd@iia2.org (starrd)", "reply_to": "<Pine.BSD.3.91.950913234317.9083H-100000@usr3.primenet.com>", "message_id": "<199509200214.MAA08618@molly.cs.monash.edu.au>"}], "subject": "Re: Scientology and police visit XS4ALL Amsterdam", "file_year": 1995, "from": "starrd <starrd@iia2.org>", "raw_date": "Thu, 14 Sep 95 19:29:27 PDT", "to": "Jiri Baum <jirib@cs.monash.edu.au>", "reply_to": "<199509130156.LAA29400@molly.cs.monash.edu.au>", "message_id": "<Pine.BSD.3.91.950913234317.9083H-100000@usr3.primenet.com>"}], "subject": "Re: Scientology and police visit XS4ALL Amsterdam", "file_year": 1995, "from": "Jiri Baum <jirib@cs.monash.edu.au>", "raw_date": "Tue, 12 Sep 95 18:59:19 PDT", "to": "starrd@iia2.org (starrd)", "reply_to": "<Pine.BSD.3.91.950907174613.22454G-100000@usr2.primenet.com>", "message_id": "<199509130156.LAA29400@molly.cs.monash.edu.au>"}], "subject": "Re: Scientology and police visit XS4ALL Amsterdam", "file_year": 1995, "from": "starrd <starrd@iia2.org>", "raw_date": "Thu, 7 Sep 95 17:58:43 PDT", "to": "Jiri Baum <jirib@cs.monash.edu.au>", "reply_to": "<199509070600.QAA11675@molly.cs.monash.edu.au>", "message_id": "<Pine.BSD.3.91.950907174613.22454G-100000@usr2.primenet.com>"}], "subject": "Re: Scientology and police visit XS4ALL Amsterdam", "file_year": 1995, "from": "Jiri Baum <jirib@cs.monash.edu.au>", "raw_date": "Wed, 6 Sep 95 23:03:18 PDT", "to": "rjc@clark.net (Ray Cromwell)", "reply_to": "<199509070346.XAA14571@clark.net>", "message_id": "<199509070600.QAA11675@molly.cs.monash.edu.au>"}], "subject": "Re: Scientology and police visit XS4ALL Amsterdam", "file_year": 1995, "from": "Ray Cromwell <rjc@clark.net>", "raw_date": "Wed, 6 Sep 95 20:46:27 PDT", "to": "cg@bofh.lake.de", "reply_to": "<m0sqR1Y-000Pa2C@bofh.lake.de>", "message_id": "<199509070346.XAA14571@clark.net>"}, {"message_hash": "0c6c2ef420f456391e8330902aa9ca3dad0698c99f879ff89f5e7f3b2e78c82b", "date": 810445759, "no_parent": null, "children": [], "subject": "Re: Scientology and police visit XS4ALL Amsterdam", "file_year": 1995, "from": "Mark <mark@lochard.com.au>", "raw_date": "Wed, 6 Sep 95 20:49:19 PDT", "to": "cg@bofh.lake.de", "reply_to": "<m0sqR1Y-000Pa2C@bofh.lake.de>", "message_id": "<199509062303.AA24688@junkers.lochard.com.au>"}], "subject": "Re: Scientology and police visit XS4ALL Amsterdam", "file_year": 1995, "from": "cg@bofh.lake.de (Cees de Groot)", "raw_date": "Wed, 6 Sep 95 13:29:12 PDT", "to": "cypherpunks@toad.com", "reply_to": null, "message_id": "<m0sqR1Y-000Pa2C@bofh.lake.de>"}], "sender_id": "cg_at_bofh_lake_de_cees_de_groot_"}