{"count": 10, "from": "\"Douglas L. Peterson\" <fnorky@chisp.net>", "threads": [{"message_hash": "6f8056833af5e38d53e857f7cfe554bebc811d88fdd2b3b77a2e67f424656822", "date": 911352041, "no_parent": null, "children": [{"message_hash": "9bc6889375f5b30f54c3377e75f663fa2ec6a0b7e7b6012146ee5e1677f54709", "date": 911385994, "no_parent": null, "children": [], "subject": "Re: FC: More on Network Associates and its crypto-politics", "file_year": 1998, "from": "\"William H. Geiger III\" <whgiii@openpgp.net>", "raw_date": "Wed, 18 Nov 1998 18:46:34 +0800", "to": "Robert Hettinga <rah@shipwright.com>", "reply_to": "<v04020a04b277c6d69429@[139.167.130.246]>", "message_id": "<199811180930.EAA005.87@whgiii>"}, {"message_hash": "c028571594bfa5b0805ebb928c8f7ee25bb1a35311d4122311e0878f8eb23826", "date": 911398481, "no_parent": null, "children": [], "subject": "Re: FC: More on Network Associates and its crypto-politics", "file_year": 1998, "from": "Declan McCullagh <declan@well.com>", "raw_date": "Wed, 18 Nov 1998 22:14:41 +0800", "to": "\"William H. Geiger III\" <rah@shipwright.com>", "reply_to": "<v04020a04b277c6d69429@[139.167.130.246]>", "message_id": "<199811181350.FAA27641@smtp.well.com>"}, {"message_hash": "a44e5b44071d6e79e77e57e994ba30aea9ea11ffdc987999e6f4a201267e8c2f", "date": 911422917, "no_parent": null, "children": [], "subject": "Re: FC: More on Network Associates and its crypto-politics", "file_year": 1998, "from": "\"Douglas L. Peterson\" <fnorky@chisp.net>", "raw_date": "Thu, 19 Nov 1998 05:01:57 +0800", "to": "Declan McCullagh <cypherpunks@Algebra.COM>", "reply_to": "<v04020a04b277c6d69429@[139.167.130.246]>", "message_id": "<36532901.A0A9255B@chisp.net>"}, {"message_hash": "75962f004d67c708bce7b63a1cc2562af32bc62a0785c65032b03d8cc7b4914e", "date": 911422960, "no_parent": null, "children": [], "subject": "Re: FC: More on Network Associates and its crypto-politics", "file_year": 1998, "from": "\"Douglas L. Peterson\" <fnorky@chisp.net>", "raw_date": "Thu, 19 Nov 1998 05:02:40 +0800", "to": "Declan McCullagh <declan@well.com>", "reply_to": "<v04020a04b277c6d69429@[139.167.130.246]>", "message_id": "<36532C1C.C79813E3@chisp.net>"}, {"message_hash": "671de46988e71fe6dca7cf8111c971f4e937ade6ebd6103f2974c2675e6c2547", "date": 911423249, "no_parent": null, "children": [], "subject": "Re: FC: More on Network Associates and its crypto-politics", "file_year": 1998, "from": "Declan McCullagh <declan@well.com>", "raw_date": "Thu, 19 Nov 1998 05:07:29 +0800", "to": "\"Douglas L. Peterson\" <cypherpunks@Algebra.COM>", "reply_to": "<v04020a04b277c6d69429@[139.167.130.246]>", "message_id": "<199811182025.MAA21320@smtp.well.com>"}], "subject": "FC: More on Network Associates and its crypto-politics", "file_year": 1998, "from": "Robert Hettinga <rah@shipwright.com>", "raw_date": "Wed, 18 Nov 1998 09:20:41 +0800", "to": "cryptography@c2.net", "reply_to": null, "message_id": "<v04020a04b277c6d69429@[139.167.130.246]>"}, {"message_hash": "f5e6d4d7312a5d9d054bfaa070b4a2fd4d1a69fb844b502a03c9479436e27edf", "date": 911458622, "no_parent": null, "children": [], "subject": "Re: CJ Update Corrected", "file_year": 1998, "from": "\"Douglas L. Peterson\" <fnorky@chisp.net>", "raw_date": "Thu, 19 Nov 1998 14:57:02 +0800", "to": "\"cypherpunks@Algebra.COM>", "reply_to": null, "message_id": "<3653B9AF.59B78D59@chisp.net>"}, {"message_hash": "db4f92cd8983ba9f2c7fb02598cfd4978bd0c0f75133117f2a4a889d0948f772", "date": 912028335, "no_parent": null, "children": [{"message_hash": "d4bbd34b8fab75b98009d2db3077b9b2d180ffcca3850f2be4a64776e99807f9", "date": 912032902, "no_parent": null, "children": [], "subject": "Re: How to reign the federal government in...", "file_year": 1998, "from": "\"Douglas L. Peterson\" <fnorky@chisp.net>", "raw_date": "Thu, 26 Nov 1998 06:28:22 +0800", "to": "Jim Choate <cypherpunks@Algebra.COM>", "reply_to": "<199811252030.OAA30458@einstein.ssz.com>", "message_id": "<365C8A52.CF56EC1C@chisp.net>"}], "subject": "How to reign the federal government in...", "file_year": 1998, "from": "Jim Choate <ravage@EINSTEIN.ssz.com>", "raw_date": "Thu, 26 Nov 1998 05:12:15 +0800", "to": "cypherpunks@EINSTEIN.ssz.com (Cypherpunks Distributed Remailer)", "reply_to": null, "message_id": "<199811252030.OAA30458@einstein.ssz.com>"}, {"message_hash": "58ac41f7d54c3277e0c10e4c430693e78b5203f1123847abbdf016d3c1ee4134", "date": 912036539, "no_parent": null, "children": [{"message_hash": "7060fe2b0950883c0f26e6cb4872713f21118ea4e4970b914afad9c8ee75541f", "date": 912036205, "no_parent": null, "children": [], "subject": "Re: Article V - an analysis", "file_year": 1998, "from": "Todd Larason <jtl@molehill.org>", "raw_date": "Thu, 26 Nov 1998 07:23:25 +0800", "to": "Jim Choate <cypherpunks@EINSTEIN.ssz.com>", "reply_to": "<199811252258.QAA31290@einstein.ssz.com>", "message_id": "<19981125145946.A9497@molehill.org>"}, {"message_hash": "36a6f28395bd54ea605e05ab68fd7f6f78c43301fa81121456e41fa58d39c017", "date": 912041620, "no_parent": null, "children": [], "subject": "Re: Article V - an analysis", "file_year": 1998, "from": "\"Douglas L. Peterson\" <fnorky@chisp.net>", "raw_date": "Thu, 26 Nov 1998 08:53:40 +0800", "to": "Jim Choate <cypherpunks@Algebra.COM>", "reply_to": "<199811252258.QAA31290@einstein.ssz.com>", "message_id": "<365CAF45.27B97897@chisp.net>"}], "subject": "Article V - an analysis", "file_year": 1998, "from": "Jim Choate <ravage@EINSTEIN.ssz.com>", "raw_date": "Thu, 26 Nov 1998 07:28:59 +0800", "to": "cypherpunks@EINSTEIN.ssz.com (Cypherpunks Distributed Remailer)", "reply_to": null, "message_id": "<199811252258.QAA31290@einstein.ssz.com>"}, {"message_hash": "02fdedddb62e409cda034d77e07e8c01afe30d4c16c41dc473f123f7fb9fce69", "date": 912034785, "no_parent": null, "children": [{"message_hash": "378d890b4174843c884af67ab13748d869e1145a33496fd86f8e09434c8a5c15", "date": 912041676, "no_parent": null, "children": [], "subject": "Re: How to reign the federal government in... (fwd)", "file_year": 1998, "from": "\"Douglas L. Peterson\" <fnorky@chisp.net>", "raw_date": "Thu, 26 Nov 1998 08:54:36 +0800", "to": "Jim Choate <cypherpunks@Algebra.COM>", "reply_to": "<199811252222.QAA31143@einstein.ssz.com>", "message_id": "<365CAEA9.791CDC76@chisp.net>"}], "subject": "Re: How to reign the federal government in... (fwd)", "file_year": 1998, "from": "Jim Choate <ravage@EINSTEIN.ssz.com>", "raw_date": "Thu, 26 Nov 1998 06:59:45 +0800", "to": "cypherpunks@EINSTEIN.ssz.com (Cypherpunks Distributed Remailer)", "reply_to": null, "message_id": "<199811252222.QAA31143@einstein.ssz.com>"}, {"message_hash": "49792ac2af2acca94a4187a07a51388225447353668f7225430c9edf93122d08", "date": 912038219, "no_parent": null, "children": [{"message_hash": "835ecb39ecf6fa70fe07cf39173fc3d39065fdb1b24dc2b180ad3b8518b89bc3", "date": 912038957, "no_parent": null, "children": [], "subject": "Re: Article V - an analysis (fwd)", "file_year": 1998, "from": "Todd Larason <jtl@molehill.org>", "raw_date": "Thu, 26 Nov 1998 08:09:17 +0800", "to": "Cypherpunks Distributed Remailer <cypherpunks@EINSTEIN.ssz.com>", "reply_to": "<199811252328.RAA31856@einstein.ssz.com>", "message_id": "<19981125153435.C9497@molehill.org>"}, {"message_hash": "b9d95f46a6f5ba0b52066f9a8dc717c356c5c3a6f71894fed50bfcceb373b708", "date": 912044910, "no_parent": null, "children": [], "subject": "Re: Article V - an analysis (fwd)", "file_year": 1998, "from": "\"Douglas L. Peterson\" <fnorky@chisp.net>", "raw_date": "Thu, 26 Nov 1998 09:48:30 +0800", "to": "Todd Larason <cypherpunks@Algebra.COM>", "reply_to": "<199811252328.RAA31856@einstein.ssz.com>", "message_id": "<365CBB46.34293003@chisp.net>"}, {"message_hash": "a89329bef61c220b49198201e642d1f993ab31ea8735b649a010963b92ed6cdc", "date": 912045448, "no_parent": null, "children": [], "subject": "Re: Article V - an analysis (fwd)", "file_year": 1998, "from": "Todd Larason <jtl@molehill.org>", "raw_date": "Thu, 26 Nov 1998 09:57:28 +0800", "to": "\"Douglas L. Peterson\" <cypherpunks@Algebra.COM>", "reply_to": "<199811252328.RAA31856@einstein.ssz.com>", "message_id": "<19981125173059.A10113@molehill.org>"}, {"message_hash": "b439ddd5aae80d4118ae8049040a0ef706ba1f125357cbffd59225e30668777c", "date": 912219505, "no_parent": null, "children": [], "subject": "Re: Article V - an analysis (fwd)", "file_year": 1998, "from": "Bill Stewart <bill.stewart@pobox.com>", "raw_date": "Sat, 28 Nov 1998 10:18:25 +0800", "to": "Cypherpunks Distributed Remailer <cypherpunks@EINSTEIN.ssz.com>", "reply_to": "<199811252328.RAA31856@einstein.ssz.com>", "message_id": "<3.0.5.32.19981127000007.008f8af0@idiom.com>"}], "subject": "Re: Article V - an analysis (fwd)", "file_year": 1998, "from": "Jim Choate <ravage@EINSTEIN.ssz.com>", "raw_date": "Thu, 26 Nov 1998 07:56:59 +0800", "to": "cypherpunks@EINSTEIN.ssz.com (Cypherpunks Distributed Remailer)", "reply_to": null, "message_id": "<199811252328.RAA31856@einstein.ssz.com>"}, {"message_hash": "56f0a07e480d12e3adf37ef0a77986b3cb050506ebfc6636d979ba266e131ad2", "date": 912882755, "no_parent": null, "children": [{"message_hash": "465d6a2675facbeefa4c6117d13526f7970d434f0b09255b371f674601b1d9ce", "date": 912885591, "no_parent": null, "children": [{"message_hash": "04ab3fa3c05caf4e9a347788c9bd531fae6d9f0d22a8ec2096f45a44917b2a88", "date": 912889030, "no_parent": null, "children": [{"message_hash": "22d8322be704f2762c4ed4880d62a1ebd358377d630223137c682405c9fd8ca0", "date": 912896479, "no_parent": null, "children": [], "subject": "Re: pgp disk", "file_year": 1998, "from": "\"Douglas L. Peterson\" <fnorky@chisp.net>", "raw_date": "Sun, 6 Dec 1998 06:21:19 +0800", "to": "\"William H. Geiger III\" <whgiii@openpgp.net>", "reply_to": "<199812051907.OAA001.57@whgiii>", "message_id": "<3669B5A0.9242EDF7@chisp.net>"}], "subject": "Re: pgp disk", "file_year": 1998, "from": "\"William H. Geiger III\" <whgiii@openpgp.net>", "raw_date": "Sun, 6 Dec 1998 04:17:10 +0800", "to": "Max Inux <maxinux@openpgp.net>", "reply_to": "<Pine.LNX.4.02.9812051155290.30678-100000@khercs.chipware.net>", "message_id": "<199812051907.OAA001.57@whgiii>"}], "subject": "Re: pgp disk", "file_year": 1998, "from": "Max Inux <maxinux@openpgp.net>", "raw_date": "Sun, 6 Dec 1998 03:19:51 +0800", "to": "HyperReal-Anon <nobody@sind.hyperreal.art.pl>", "reply_to": "<fb4d35c7250a01fc0610606c695e3e20@anonymous>", "message_id": "<Pine.LNX.4.02.9812051155290.30678-100000@khercs.chipware.net>"}], "subject": "pgp disk", "file_year": 1998, "from": "HyperReal-Anon <nobody@sind.hyperreal.art.pl>", "raw_date": "Sun, 6 Dec 1998 02:32:35 +0800", "to": "cypherpunks@Algebra.COM", "reply_to": null, "message_id": "<fb4d35c7250a01fc0610606c695e3e20@anonymous>"}, {"message_hash": "892f8bf5ef45828e1ba7575058b90a2ede41159ac220006c4e60c75159510065", "date": 912310131, "no_parent": null, "children": [{"message_hash": "8ee178024cff11bf00e9aaba172ee0c81591972b9f2d16604157b22140a1f893", "date": 912798909, "no_parent": null, "children": [{"message_hash": "d9ea4507d4730a81eefb3c64cd12bafbc72de29baac15032dd607922e900ea3c", "date": 912807083, "no_parent": null, "children": [{"message_hash": "836c770ee8c43fa3de4d6fb800d2b232f9afa041b1679c294e38f0bf327f4c5a", "date": 912817491, "no_parent": null, "children": [{"message_hash": "63798d63fe82d8afd504180b44b8aed8380fe8984d5a2f65105d0a48f67fe36a", "date": 912820086, "no_parent": null, "children": [{"message_hash": "96f362300798853548a6a252b737e31997512cf69c69e5271bcd3dd92aaf0979", "date": 912867162, "no_parent": null, "children": [{"message_hash": "bc4de33ada071bf8eaf186c31c4ee34eca5ef3d1dcf7ea84fb62906bea8b6ec5", "date": 912874955, "no_parent": null, "children": [{"message_hash": "c08638651919188e478a419e2fcbe2c8df7dd055c07241170db10ca71164b80b", "date": 912923374, "no_parent": null, "children": [{"message_hash": "4fdb40c3690158ffa1dcdd11f0f210fcfb742d333caf3e18acc71bc660830506", "date": 912979243, "no_parent": null, "children": [], "subject": "Re: y2k/gary north delusions", "file_year": 1998, "from": "ichudov@Algebra.COM (Igor Chudov @ home)", "raw_date": "Mon, 7 Dec 1998 05:20:43 +0800", "to": "mah248@nyu.edu (Michael Hohensee)", "reply_to": "<366A26C2.30D6892E@nyu.edu>", "message_id": "<199812062044.OAA12076@manifold.algebra.com>"}, {"message_hash": "ea4e6ae683d1c55649b059277cafe367ea69c9231b6ea4a4baa87b8037bc5074", "date": 912980421, "no_parent": null, "children": [{"message_hash": "c8d4d38194ffd96140701811857d2539e545c2d5a0fc13170676f13e1534d02f", "date": 912994858, "no_parent": null, "children": [], "subject": "Re: y2k/gary north delusions", "file_year": 1998, "from": "Michael Hohensee <michael@sparta.mainstream.net>", "raw_date": "Mon, 7 Dec 1998 09:40:58 +0800", "to": "cypherpunks@cyberpass.net", "reply_to": "<199812062023.PAA001.79@whgiii>", "message_id": "<366B17BF.963FFEA@sparta.mainstream.net>"}, {"message_hash": "6053a83fe3dbe0eef5a012b7b5ac16b9b510bed9829c777465d1b50652173466", "date": 913090804, "no_parent": null, "children": [], "subject": "Re: y2k/gary north delusions", "file_year": 1998, "from": "\"Douglas L. Peterson\" <fnorky@chisp.net>", "raw_date": "Tue, 8 Dec 1998 12:20:04 +0800", "to": "\"William H. Geiger III\" <cypherpunks@Algebra.COM>", "reply_to": "<199812062023.PAA001.79@whgiii>", "message_id": "<366CAFEE.583BC1DE@chisp.net>"}], "subject": "Re: y2k/gary north delusions", "file_year": 1998, "from": "\"William H. Geiger III\" <whgiii@openpgp.net>", "raw_date": "Mon, 7 Dec 1998 05:40:21 +0800", "to": "Michael Hohensee <mah248@nyu.edu>", "reply_to": "<366A26C2.30D6892E@nyu.edu>", "message_id": "<199812062023.PAA001.79@whgiii>"}, {"message_hash": "f2e426059f30647098b6d94eaaa4b2596b21934132efe704fd8bccd8d9b831d0", "date": 913066679, "no_parent": null, "children": [], "subject": "Re: y2k/gary north delusions", "file_year": 1998, "from": "Petro <petro@playboy.com>", "raw_date": "Tue, 8 Dec 1998 05:37:59 +0800", "to": "cypherpunks@cyberpass.net", "reply_to": "<366A26C2.30D6892E@nyu.edu>", "message_id": "<v04011703b291d39dc7f5@[207.138.127.230]>"}], "subject": "Re: y2k/gary north delusions", "file_year": 1998, "from": "Michael Hohensee <mah248@nyu.edu>", "raw_date": "Sun, 6 Dec 1998 13:49:34 +0800", "to": "cypherpunks@cyberpass.net", "reply_to": "<199812051511.KAA001.50@whgiii>", "message_id": "<366A26C2.30D6892E@nyu.edu>"}], "subject": "Re: y2k/gary north delusions", "file_year": 1998, "from": "\"William H. Geiger III\" <whgiii@openpgp.net>", "raw_date": "Sun, 6 Dec 1998 00:22:35 +0800", "to": "Michal Hohensee <mah248@nyu.edu>", "reply_to": "<36694C23.B4CB9509@nyu.edu>", "message_id": "<199812051511.KAA001.50@whgiii>"}, {"message_hash": "44b093023bb4cf5827eff59a2bff8342f0aefbe5db7deac3f0d7f50f24501afd", "date": 912877703, "no_parent": null, "children": [{"message_hash": "7496f56b1d1e4cb28abd983a38454cb42ae48aad39269ce12fd9d8f0b31f5223", "date": 912923498, "no_parent": null, "children": [{"message_hash": "a11f8ab1f7cc13f9d911e98bd43185be9b933a46849ffa02abf9c7b5d604089e", "date": 912979706, "no_parent": null, "children": [], "subject": "No food, no shit (Re: y2k/gary north delusionsn)", "file_year": 1998, "from": "ichudov@Algebra.COM (Igor Chudov @ home)", "raw_date": "Mon, 7 Dec 1998 05:28:26 +0800", "to": "mah248@nyu.edu (Michael Hohensee)", "reply_to": "<366A2610.7F850BA3@nyu.edu>", "message_id": "<199812062043.OAA12057@manifold.algebra.com>"}], "subject": "Re: y2k/gary north delusions", "file_year": 1998, "from": "Michael Hohensee <mah248@nyu.edu>", "raw_date": "Sun, 6 Dec 1998 13:51:38 +0800", "to": "cypherpunks@cyberpass.net", "reply_to": "<199812051640.KAA04447@manifold.algebra.com>", "message_id": "<366A2610.7F850BA3@nyu.edu>"}], "subject": "Re: y2k/gary north delusions", "file_year": 1998, "from": "ichudov@Algebra.COM (Igor Chudov @ home)", "raw_date": "Sun, 6 Dec 1998 01:08:23 +0800", "to": "mah248@nyu.edu (Michal Hohensee)", "reply_to": "<36694C23.B4CB9509@nyu.edu>", "message_id": "<199812051640.KAA04447@manifold.algebra.com>"}, {"message_hash": "92d9c163941413285eb62b126b15a6862286f261c04fde963609bedb30f1cc95", "date": 913066563, "no_parent": null, "children": [], "subject": "Re: y2k/gary north delusions", "file_year": 1998, "from": "Petro <petro@playboy.com>", "raw_date": "Tue, 8 Dec 1998 05:36:03 +0800", "to": "\"William H. Geiger III\" <mah248@nyu.edu>", "reply_to": "<36694C23.B4CB9509@nyu.edu>", "message_id": "<v04011702b291bf16f5c7@[207.138.127.230]>"}], "subject": "Re: y2k/gary north delusions", "file_year": 1998, "from": "Michal Hohensee <mah248@nyu.edu>", "raw_date": "Sat, 5 Dec 1998 22:12:42 +0800", "to": "cypherpunks@cyberpass.net", "reply_to": "<199812050047.SAA19462@manifold.algebra.com>", "message_id": "<36694C23.B4CB9509@nyu.edu>"}, {"message_hash": "1aa04ff87fe181d8ac0c3fd00ba414320b87270162f98de61258c41ede9569cf", "date": 912871541, "no_parent": null, "children": [], "subject": "Re: y2k/gary north delusions", "file_year": 1998, "from": "Soren <sorens@workmail.com>", "raw_date": "Sat, 5 Dec 1998 23:25:41 +0800", "to": "cyphers <cypherpunks@cyberpass.net>", "reply_to": "<199812050047.SAA19462@manifold.algebra.com>", "message_id": "<366958DF.FBF816FC@workmail.com>"}, {"message_hash": "570b823657174bb548f129832613d4f7c87edd6c8882cbe5234b4465c491d124", "date": 912875478, "no_parent": null, "children": [], "subject": "Re: y2k/gary north delusions", "file_year": 1998, "from": "John Young <jya@pipeline.com>", "raw_date": "Sun, 6 Dec 1998 00:31:18 +0800", "to": "cypherpunks@EINSTEIN.ssz.com", "reply_to": "<199812050047.SAA19462@manifold.algebra.com>", "message_id": "<199812051605.LAA01045@camel14.mindspring.com>"}, {"message_hash": "d0e2fa780abec087928c601694b85a45c46d9c96c70f0cb3c40ff1a58ece56bc", "date": 912887368, "no_parent": null, "children": [], "subject": "Re: y2k/gary north delusions", "file_year": 1998, "from": "Declan McCullagh <declan@well.com>", "raw_date": "Sun, 6 Dec 1998 03:49:28 +0800", "to": "Soren <cypherpunks@cyberpass.net>", "reply_to": "<199812050047.SAA19462@manifold.algebra.com>", "message_id": "<199812051926.LAA10339@smtp.well.com>"}, {"message_hash": "782902b37c150ed455b0a8ecae574f39840e4ac561a4e3c2e5baed8de9bbeb72", "date": 912922517, "no_parent": null, "children": [], "subject": "Re: y2k/gary north delusions", "file_year": 1998, "from": "Michael Hohensee <mah248@nyu.edu>", "raw_date": "Sun, 6 Dec 1998 13:35:17 +0800", "to": "cypherpunks@cyberpass.net", "reply_to": "<199812050047.SAA19462@manifold.algebra.com>", "message_id": "<366A2313.DF9FA151@nyu.edu>"}], "subject": "Re: y2k/gary north delusions", "file_year": 1998, "from": "ichudov@Algebra.COM (Igor Chudov @ home)", "raw_date": "Sat, 5 Dec 1998 09:08:06 +0800", "to": "mah248@nyu.edu (Michal Hohensee)", "reply_to": "<36688ACA.C9F515B3@nyu.edu>", "message_id": "<199812050047.SAA19462@manifold.algebra.com>"}], "subject": "Re: y2k/gary north delusions", "file_year": 1998, "from": "Michal Hohensee <mah248@nyu.edu>", "raw_date": "Sat, 5 Dec 1998 08:24:51 +0800", "to": "cypherpunks@cyberpass.net", "reply_to": "<199812042048.OAA15267@manifold.algebra.com>", "message_id": "<36688ACA.C9F515B3@nyu.edu>"}], "subject": "Re: y2k/gary north delusions", "file_year": 1998, "from": "ichudov@Algebra.COM (Igor Chudov @ home)", "raw_date": "Sat, 5 Dec 1998 05:31:23 +0800", "to": "petro@playboy.com (Petro)", "reply_to": "<v04011706b2889eb2b6a8@[206.189.103.230]>", "message_id": "<199812042048.OAA15267@manifold.algebra.com>"}, {"message_hash": "0e4d2975a482a17a9fa7c100152b06be9f572acef7329553fe9f31406d233b34", "date": 912813759, "no_parent": null, "children": [{"message_hash": "51105fb7dbd4a3867d5b4eaa0312d46d787693f8da363ae470f2dc755d4d218a", "date": 912817697, "no_parent": null, "children": [{"message_hash": "0f2ff0350249181853752c51e8a27b64fd46d26a16f27806755919289f3b6ff5", "date": 913066757, "no_parent": null, "children": [], "subject": "Re: [Fwd: y2k/gary north delusions]", "file_year": 1998, "from": "Petro <petro@playboy.com>", "raw_date": "Tue, 8 Dec 1998 05:39:17 +0800", "to": "cypherpunks@cyberpass.net", "reply_to": "<199812042341.RAA18742@manifold.algebra.com>", "message_id": "<v04011701b291be28bde1@[207.138.127.230]>"}], "subject": "Re: y2k/gary north delusions", "file_year": 1998, "from": "ichudov@Algebra.COM (Igor Chudov @ home)", "raw_date": "Sat, 5 Dec 1998 08:28:17 +0800", "to": "petro@playboy.com (Petro)", "reply_to": "<v04011703b28df9c5afbe@[206.189.103.230]>", "message_id": "<199812042341.RAA18742@manifold.algebra.com>"}], "subject": "Re: y2k/gary north delusions", "file_year": 1998, "from": "Petro <petro@playboy.com>", "raw_date": "Sat, 5 Dec 1998 07:22:39 +0800", "to": "ichudov@Algebra.COM (Igor Chudov)", "reply_to": "<v04011706b2889eb2b6a8@[206.189.103.230]>", "message_id": "<v04011703b28df9c5afbe@[206.189.103.230]>"}], "subject": "Re: y2k/gary north delusions", "file_year": 1998, "from": "Petro <petro@playboy.com>", "raw_date": "Sat, 5 Dec 1998 03:15:09 +0800", "to": "cypherpunks@cyberpass.net", "reply_to": "<199811290304.TAA06582@netcom13.netcom.com>", "message_id": "<v04011706b2889eb2b6a8@[206.189.103.230]>"}], "subject": "y2k/gary north delusions", "file_year": 1998, "from": "\"Vladimir Z. Nuri\" <vznuri@netcom.com>", "raw_date": "Sun, 29 Nov 1998 11:28:51 +0800", "to": "cypherpunks@cyberpass.net", "reply_to": null, "message_id": "<199811290304.TAA06582@netcom13.netcom.com>"}, {"message_hash": "c963950e0aeb96c37678449c8c84c450c30c06e87535b7c5d5ce4a7bc69a8214", "date": 915135202, "no_parent": null, "children": [], "subject": "Englewood seeks limit on Net sex sites", "file_year": 1999, "from": "\"Douglas L. Peterson\" <fnorky@chisp.net>", "raw_date": "Fri, 1 Jan 1999 04:13:22 +0800", "to": "Cypherpunks Distributed Remailer <cypherpunks@Algebra.COM>", "reply_to": null, "message_id": "<368BE358.BC07E252@chisp.net>"}], "sender_id": "douglas_l_peterson_fnorky_at_chisp_net_"}