{"count": 1, "from": "get.a.life@worldnet.att.net", "threads": [{"message_hash": "d2efd287fa28b488d20bf00a900d43e8c1ab498d62f2b3020a5c9f879b12b1e8", "date": 856655684, "no_parent": null, "children": [], "subject": "Tap in to You Income Potential", "file_year": 1997, "from": "get.a.life@worldnet.att.net", "raw_date": "Sat, 22 Feb 1997 15:54:44 -0800 (PST)", "to": "cypherpunks@toad.com", "reply_to": null, "message_id": "<19970222223625.AUJ19585@mailhost.worldnet.att.net>"}], "sender_id": "get_a_life_at_worldnet_att_net"}