{"count": 1, "from": "greg@amex-trs.com (Greg Thompson)", "threads": [{"message_hash": "70cb75b16fa22389f4ff827e75ca6b0587e24bdc7e6d89d5012f58f4efe19d2b", "date": 735265505, "no_parent": null, "children": [], "subject": "Subscribing", "file_year": 1993, "from": "greg@amex-trs.com (Greg Thompson)", "raw_date": "Mon, 19 Apr 93 17:25:05 PDT", "to": "cypherpunks@toad.com", "reply_to": null, "message_id": "<9304192016.AA39795@tonga.cs90-dev.amex-trs.com>"}], "sender_id": "greg_at_amextrs_com_greg_thompson_"}