{"count": 2, "from": "Howard Campbell <woody@hi.net>", "threads": [{"message_hash": "01e1cb2129a96adc01b72b6a0a8db42c25897b0caf9b34e0bf7f0bd157ae8cb7", "date": 854345279, "no_parent": null, "children": [], "subject": "re: fighting the cybercensor", "file_year": 1997, "from": "Howard Campbell <woody@hi.net>", "raw_date": "Sun, 26 Jan 1997 22:07:59 -0800 (PST)", "to": "cypherpunks@toad.com", "reply_to": null, "message_id": "<199701270611.UAA04805@pohaku.hi.net>"}, {"message_hash": "1eb27ca2974064eff8acb368acf802a9f3fb2407e0e516567c5d30b693ff6440", "date": 854348267, "no_parent": null, "children": [], "subject": "re: fighting the cybercensor", "file_year": 1997, "from": "Howard Campbell <woody@hi.net>", "raw_date": "Sun, 26 Jan 1997 22:57:47 -0800 (PST)", "to": "cypherpunks@toad.com", "reply_to": null, "message_id": "<199701270657.WAA13589@toad.com>"}], "sender_id": "howard_campbell_woody_at_hi_net_"}