{"count": 1, "from": "\"Jim Grubs (W8GRT)\" <jgrubs@webcasters.com>", "threads": [{"message_hash": "70e9cca7aa53313125a7a9ec35c86053b002c6bce53e68b2938d3cd17f781489", "date": 813084133, "no_parent": null, "children": [], "subject": "Kerserver keyrings", "file_year": 1995, "from": "\"Jim Grubs (W8GRT)\" <jgrubs@webcasters.com>", "raw_date": "Sat, 7 Oct 95 09:42:13 PDT", "to": "\"cypherpunks@toad.com>", "reply_to": null, "message_id": "<199510071639.MAA29272@norden1.com>"}], "sender_id": "jim_grubs_w8grt__jgrubs_at_webcasters_com_"}