{"count": 1, "from": "Jordan Hayes <jordan@Have.You.Seen.My.Infomercial.COM>", "threads": [{"message_hash": "0522dbab500ee8f28809379cfbc472f6edaf6ffcff3b5c077eb97cec23f087d5", "date": 831243828, "no_parent": null, "children": [{"message_hash": "71ccee1d6fff5440523679f75bc2cea91dca9655d4759f0358468000ce20edc7", "date": 831264049, "no_parent": null, "children": [], "subject": "Re: CryptoAnarchy: What's wrong with this picture?", "file_year": 1996, "from": "Black Unicorn <unicorn@schloss.li>", "raw_date": "Sun, 5 May 1996 10:40:49 +0800", "to": "Jordan Hayes <jordan@Have.You.Seen.My.Infomercial.COM>", "reply_to": "<199605041609.JAA21395@Thinkbank.COM>", "message_id": "<Pine.SUN.3.93.960504182204.16238C-100000@polaris.mindport.net>"}], "subject": "Re: CryptoAnarchy: What's wrong with this picture?", "file_year": 1996, "from": "Jordan Hayes <jordan@Have.You.Seen.My.Infomercial.COM>", "raw_date": "Sun, 5 May 1996 05:03:48 +0800", "to": "cypherpunks@toad.com", "reply_to": null, "message_id": "<199605041609.JAA21395@Thinkbank.COM>"}], "sender_id": "jordan_hayes_jordan_at_have_you_seen_my_infomercial_com_"}