{"count": 2, "from": "Marianne Mueller <mrrm@well.sf.ca.us>", "threads": [{"message_hash": "3a1beafc5a342867ea75a8c1eec6b511a5793ea32844f26e6d5f9ef27e872bfe", "date": 737847785, "no_parent": null, "children": [{"message_hash": "2c616cd79c21e3c7a3bd3addb599e4782024afb5fca0e208771b7a4e3d6e3a3c", "date": 737850009, "no_parent": null, "children": [], "subject": "Consider \"Working Assets\" phone service instead of AT&T", "file_year": 1993, "from": "jet@nas.nasa.gov (J. Eric Townsend)", "raw_date": "Wed, 19 May 93 15:20:09 PDT", "to": "cypherpunks@toad.com", "reply_to": "<199305192142.AA25642@well.sf.ca.us>", "message_id": "<9305192220.AA00742@boxer.nas.nasa.gov>"}, {"message_hash": "8a10b57790912a23f1061f60c5befa73510db7fe9e0f90df93c6e083d34a7e44", "date": 737851276, "no_parent": null, "children": [], "subject": "Re: Consider \"Working Assets\" phone service instead of AT&T", "file_year": 1993, "from": "\"Perry E. Metzger\" <pmetzger@lehman.com>", "raw_date": "Wed, 19 May 93 15:41:16 PDT", "to": "Marianne Mueller <mrrm@well.sf.ca.us>", "reply_to": "<199305192142.AA25642@well.sf.ca.us>", "message_id": "<9305192239.AA05954@snark.shearson.com>"}], "subject": "Consider \"Working Assets\" phone service instead of AT&T", "file_year": 1993, "from": "Marianne Mueller <mrrm@well.sf.ca.us>", "raw_date": "Wed, 19 May 93 14:43:05 PDT", "to": "cypherpunks@toad.com", "reply_to": null, "message_id": "<199305192142.AA25642@well.sf.ca.us>"}, {"message_hash": "1ee2b1cc1bda0ee7f32cc8200e2b722bb486d76fa7b858ae5fe0a7a383a29fdd", "date": 740266132, "no_parent": null, "children": [], "subject": "Draft Solaris Teleservices API doc, anon ftp", "file_year": 1993, "from": "Marianne Mueller <mrrm@well.sf.ca.us>", "raw_date": "Wed, 16 Jun 93 14:28:52 PDT", "to": "cypherpunks@toad.com", "reply_to": null, "message_id": "<93Jun16.142816pdt.13877-2@well.sf.ca.us>"}], "sender_id": "marianne_mueller_mrrm_at_well_sf_ca_us_"}