{"count": 9, "from": "mf@mediafilter.org (MediaFilter)", "threads": [{"message_hash": "92eeb5e70825902def615974d52f1ab22d394e64ce6d578039d27293611a70a8", "date": 850301385, "no_parent": null, "children": [], "subject": "black.hole in the net", "file_year": 1996, "from": "mf@MediaFilter.org (MediaFilter)", "raw_date": "Wed, 11 Dec 1996 02:49:45 -0800 (PST)", "to": "eon@black.hole", "reply_to": null, "message_id": "<1361846569-1146094@MediaFilter.org>"}, {"message_hash": "70b4ec4295115cb0ed2d26c6b7b0fac353a60a19f8415cd2872a161ff04f82f5", "date": 850303358, "no_parent": null, "children": [], "subject": "Much Ado About Names", "file_year": 1996, "from": "mf@MediaFilter.org (MediaFilter)", "raw_date": "Wed, 11 Dec 1996 03:22:38 -0800 (PST)", "to": "eon@black.hole", "reply_to": null, "message_id": "<1361845458-1212940@MediaFilter.org>"}, {"message_hash": "2e03b50f1e257cec95aa509cf9b8108788a82181dc4c41c127adf6d8b265020f", "date": 850728774, "no_parent": null, "children": [], "subject": "name.space. call for content", "file_year": 1996, "from": "mf@MediaFilter.org (MediaFilter)", "raw_date": "Mon, 16 Dec 1996 01:32:54 -0800 (PST)", "to": "eon@black.hole", "reply_to": null, "message_id": "<1361416246-7199575@MediaFilter.org>"}, {"message_hash": "94c3facc32079c8d72d535bce4d766b8f28c0ebee1c23bb79610701a8e7f1d9e", "date": 858926746, "no_parent": null, "children": [], "subject": "PGP Media Sues NSI To Open the Domain Name Registration Market", "file_year": 1997, "from": "mf@MediaFilter.org (MediaFilter)", "raw_date": "Thu, 20 Mar 1997 22:45:46 -0800 (PST)", "to": "eon@black.hole", "reply_to": null, "message_id": "<1353214228-802615@MediaFilter.org>"}, {"message_hash": "f743383540b78a6f1b174ca3f36577134bc4aad9b89a900ec5b02f1cc3c8fe53", "date": 863089048, "no_parent": null, "children": [], "subject": "pgMedia, Inc. vs. Network Solutions, Inc. PARTY!", "file_year": 1997, "from": "mf@mediafilter.org (MediaFilter)", "raw_date": "Thu, 8 May 1997 03:57:28 -0700 (PDT)", "to": "eon@black.hole", "reply_to": null, "message_id": "<1349049079-807401@MediaFilter.org>"}, {"message_hash": "a52a17986d43986fe2f7079d1c420b2a56c58bf20cda1276ec85a4bbad14c6ba", "date": 864202815, "no_parent": null, "children": [], "subject": "Disneyfication, Privatization of the Public Domain...\tTurn the Planet into a Strip-Mall and Theme Park.....", "file_year": 1997, "from": "mf@mediafilter.org (MediaFilter)", "raw_date": "Wed, 21 May 1997 01:20:15 -0700 (PDT)", "to": "eon@black.hole", "reply_to": null, "message_id": "<1347936075-200645@MediaFilter.org>"}, {"message_hash": "367d075e521c3d81b976f948451be46b457a708aeb729480a0e3212604ec3094", "date": 864212750, "no_parent": null, "children": [], "subject": "Disneyfication, Privatization of the Public Domain...\tTurn the Planet into a Strip-Mall and Theme Park.....\tCorection!", "file_year": 1997, "from": "mf@mediafilter.org (MediaFilter)", "raw_date": "Wed, 21 May 1997 04:05:50 -0700 (PDT)", "to": "eon@black.hole", "reply_to": null, "message_id": "<1347929820-576932@MediaFilter.org>"}, {"message_hash": "d845de0fc197017b22674b916522122b026ca1e3ec2a122ea49d32c98d3cb1aa", "date": 869992966, "no_parent": null, "children": [], "subject": "Re: Netzwelt: Geiselnahme im Netz (article in DER SPIEGEL)", "file_year": 1997, "from": "mf@mediafilter.org (MediaFilter)", "raw_date": "Sun, 27 Jul 1997 01:42:46 -0700 (PDT)", "to": "(Recipient list suppressed)", "reply_to": null, "message_id": "<1342145713-807839@MediaFilter.org>"}, {"message_hash": "5501628c9e67a1b53bec7d73a1a1ecec4aa80818fe26e84a8ca25962f7e77677", "date": 888250375, "no_parent": null, "children": [], "subject": "CryptoGate, from CAQ", "file_year": 1998, "from": "mf@mediafilter.org (MediaFilter)", "raw_date": "Mon, 23 Feb 1998 08:12:55 -0800 (PST)", "to": "cypherpunks@toad.com", "reply_to": null, "message_id": "<1323889970-327546@mediafilter.org>"}], "sender_id": "mf_at_mediafilter_org_mediafilter_"}