{"count": 1, "from": "Michael <wk01847@worldlink.com>", "threads": [{"message_hash": "a205e3592196c3eea1af72dd18a2158b27f1f1620d5488a2dc26994c9e7ca33b", "date": 731493591, "no_parent": null, "children": [], "subject": "Re: F-117A Nighthawk pseudo\"revelation\".", "file_year": 1993, "from": "Michael <wk01847@worldlink.com>", "raw_date": "Sun, 7 Mar 93 00:39:51 PST", "to": "Alfred Martinez <75300.717@compuserve.com>", "reply_to": null, "message_id": "<9303070838.AA00566@worldlink.worldlink.com>"}], "sender_id": "michael_wk01847_at_worldlink_com_"}