{"count": 1, "from": "Miguel Saraiva <msaraiva@marktest.pt>", "threads": [{"message_hash": "6aef0559e35e55fd84853f2aaa75dfabeb57e6d07f861663306aa0e1cd984c90", "date": 823166550, "no_parent": null, "children": [], "subject": "RE: Netscape encrypted email!!", "file_year": 1996, "from": "Miguel Saraiva <msaraiva@marktest.pt>", "raw_date": "Thu, 1 Feb 1996 17:22:30 +0800", "to": "\"'cypherpunks@toad.com>", "reply_to": null, "message_id": "<01BAEFC3.C50F85E0@leon.marktest.pt>"}], "sender_id": "miguel_saraiva_msaraiva_at_marktest_pt_"}