{"count": 1, "from": "Neal.McBurnett@att.com (Neal McBurnett)", "threads": [{"message_hash": "167415c686d531afebca509b9502907cf21c6352368b5876161afc565c746bae", "date": 823327386, "no_parent": null, "children": [{"message_hash": "de3c14412ccc66b9faf74b9455f2951d4d58ae3cbb0daea5224ac4bfe6ea3975", "date": 823328569, "no_parent": null, "children": [], "subject": "Re: Analysis of PGP keyserver web of trust", "file_year": 1996, "from": "Simon Spero <ses@tipper.oit.unc.edu>", "raw_date": "Sat, 3 Feb 1996 14:22:49 +0800", "to": "Neal McBurnett <Neal.McBurnett@att.com>", "reply_to": "<9602030545.AA06363@lever.dr.att.com>", "message_id": "<Pine.SOL.3.91.960202220137.12585A-100000@chivalry>"}], "subject": "Analysis of PGP keyserver web of trust", "file_year": 1996, "from": "Neal.McBurnett@att.com (Neal McBurnett)", "raw_date": "Sat, 3 Feb 1996 14:03:06 +0800", "to": "cypherpunks@toad.com", "reply_to": null, "message_id": "<9602030545.AA06363@lever.dr.att.com>"}], "sender_id": "neal_mcburnett_at_att_com_neal_mcburnett_"}