{"count": 1, "from": "Ole Jacobsen <olejac@post4.tele.dk>", "threads": [{"message_hash": "5cae83bba4c205eecbb7f03c85369118535e4eaa9a899c6774bccaf9daf19019", "date": 884268455, "no_parent": null, "children": [{"message_hash": "46e6bda1922a0875b687d53bbacac2f5bc5abaab0835e30268488df644a36e8d", "date": 884283942, "no_parent": null, "children": [], "subject": "Re: UNSUBSCRIBE CYPHERPUNKS-ANNOUNCE", "file_year": 1998, "from": "Ole Jacobsen <olejac@post4.tele.dk>", "raw_date": "Thu, 8 Jan 1998 10:25:42 -0800 (PST)", "to": "\"brian@csihost.4qsi.com>", "reply_to": "<9801080907.ZM10801@csihost.4qsi.com>", "message_id": "<34B50B55.4F04@post4.tele.dk>"}], "subject": "UNSUBSCRIBE CYPHERPUNKS-ANNOUNCE", "file_year": 1998, "from": "\"bRIAN@4qsi.com\" <brian@csihost.4qsi.com>", "raw_date": "Thu, 8 Jan 1998 06:07:35 -0800 (PST)", "to": "cypherpunks-announce@toad.com", "reply_to": null, "message_id": "<9801080907.ZM10801@csihost.4qsi.com>"}], "sender_id": "ole_jacobsen_olejac_at_post4_tele_dk_"}