{"count": 1, "from": "patm@connix.com (Pat McCotter)", "threads": [{"message_hash": "6658c2d46530b1b52d4655adf945a71c9ab8607f1b16f734c5959ee6b4f3184d", "date": 848365936, "no_parent": null, "children": [{"message_hash": "8f6372311adcca945879742d9b850a8f56780dbd9c403df743fe6f145b9a1997", "date": 848384771, "no_parent": null, "children": [], "subject": "Re: Extreme Left/Right", "file_year": 1996, "from": "Jeremiah A Blatz <jer+@andrew.cmu.edu>", "raw_date": "Mon, 18 Nov 1996 22:26:11 -0800 (PST)", "to": "cypherpunks@toad.com", "reply_to": "<Pine.HPP.3.91.961118184355.23458G-100000@hpg60.astea.com>", "message_id": "<0mYJ==200YUe083bw0@andrew.cmu.edu>"}, {"message_hash": "4f48fdfc0a32d36e728ae1b3ca309b3fa0070719bb5119f7ce1a63aae6d156e1", "date": 848385989, "no_parent": null, "children": [], "subject": "Re: Extreme Left/Right", "file_year": 1996, "from": "\"William H. Geiger III\" <whgiii@amaranth.com>", "raw_date": "Mon, 18 Nov 1996 22:46:29 -0800 (PST)", "to": "James Ormond <jimo@astea.com>", "reply_to": "<Pine.HPP.3.91.961118184355.23458G-100000@hpg60.astea.com>", "message_id": "<199611190801.CAA00778@mailhub.amaranth.com>"}, {"message_hash": "703a9767294e31dbc5fb738329a3e2fc26c125267da81041e105ce09031aab4e", "date": 848387700, "no_parent": null, "children": [], "subject": "Re: Extreme Left/Right", "file_year": 1996, "from": "Dale Thorn <dthorn@gte.net>", "raw_date": "Mon, 18 Nov 1996 23:15:00 -0800 (PST)", "to": "James Ormond <jimo@astea.com>", "reply_to": "<Pine.HPP.3.91.961118184355.23458G-100000@hpg60.astea.com>", "message_id": "<32915E11.3DBE@gte.net>"}, {"message_hash": "a86e28fafb22b6b70728382d0e254f49ced0899361ae3e67e39d9059770b9683", "date": 848394470, "no_parent": null, "children": [], "subject": "Re: Extreme Left/Right", "file_year": 1996, "from": "patm@connix.com (Pat McCotter)", "raw_date": "Tue, 19 Nov 1996 01:07:50 -0800 (PST)", "to": "cypherpunks@toad.com", "reply_to": "<Pine.HPP.3.91.961118184355.23458G-100000@hpg60.astea.com>", "message_id": "<329174bc.8030604@smtp.connix.com>"}], "subject": "Extreme Left/Right", "file_year": 1996, "from": "James Ormond <jimo@astea.com>", "raw_date": "Mon, 18 Nov 1996 17:12:16 -0800 (PST)", "to": "Sandy Sandfort <sandfort@crl.com>", "reply_to": null, "message_id": "<Pine.HPP.3.91.961118184355.23458G-100000@hpg60.astea.com>"}], "sender_id": "patm_at_connix_com_pat_mccotter_"}