{"count": 1, "from": "registrar@mailer.switchboard.com (Switchboard Registrar)", "threads": [{"message_hash": "514c1b8fa090d96ed048e130451c8993c9ac1f4ff3fc4c01f0471b0641f7d08f", "date": 906700681, "no_parent": null, "children": [], "subject": "Welcome to Switchboard: [FBJJM,695]", "file_year": 1998, "from": "registrar@mailer.switchboard.com (Switchboard Registrar)", "raw_date": "Fri, 25 Sep 1998 13:18:01 +0800", "to": "cypherpunks@toad.com", "reply_to": null, "message_id": "<19980925180408454.AAA87@www1>"}], "sender_id": "registrar_at_mailer_switchboard_com_switchboard_registrar_"}