{"count": 3, "from": "remove@structuremg.com", "threads": [{"message_hash": "7d7a38c892e454243684560e1136cadad0de4a5ccf884402d7f6ab8ac39e8493", "date": 853759396, "no_parent": null, "children": [], "subject": "Too much week at the end of your paycheck?", "file_year": 1997, "from": "remove@structuremg.com", "raw_date": "Mon, 20 Jan 1997 03:23:16 -0800 (PST)", "to": "cypherpunks@toad.com", "reply_to": null, "message_id": "<Ready Aim Fire!_1/20/97 6:23:05 AM_remove@structuremg.com>"}, {"message_hash": "e86142a3ecff2d62620fdb7181e6e831a083dc3329f5395adaa6f453290bc6f5", "date": 856329949, "no_parent": null, "children": [], "subject": "7.9 cpm long-distance", "file_year": 1997, "from": "remove@structuremg.com", "raw_date": "Tue, 18 Feb 1997 21:25:49 -0800 (PST)", "to": "cypherpunks@toad.com", "reply_to": null, "message_id": "<Ready Aim Fire!_2/19/97 12:25:48 AM_remove@structuremg.com>"}, {"message_hash": "a9a4bc3b14e1dadfa6977df4fb429765754470b33491f06de043775ba6d5b87a", "date": 856331879, "no_parent": null, "children": [], "subject": "7.9 cpm long-distance", "file_year": 1997, "from": "remove@structuremg.com", "raw_date": "Tue, 18 Feb 1997 21:57:59 -0800 (PST)", "to": "cypherpunks@toad.com", "reply_to": null, "message_id": "<199702190557.VAA18720@toad.com>"}], "sender_id": "remove_at_structuremg_com"}