{"count": 1, "from": "\"Sam 'MaCpHReaK'  Chua\" <samchua@singnet.com.sg>", "threads": [{"message_hash": "fea56189eb4dde6f2c5bc0b8c658d331d0968cbd0ec4cee6eda9f76db3638668", "date": 874275397, "no_parent": null, "children": [{"message_hash": "a705c4d1cbd35c7d18d7a6e4e5dabe42f95e8c809951766d8619da7a1da613cc", "date": 874279074, "no_parent": null, "children": [], "subject": "Re: Proxies", "file_year": 1997, "from": "\"Mark M.\" <markm@voicenet.com>", "raw_date": "Mon, 15 Sep 1997 07:17:54 +0800", "to": "\"Sam 'MaCpHReaK'  Chua\" <samchua@singnet.com.sg>", "reply_to": "<v03110701b04209789665@[165.21.186.199]>", "message_id": "<Pine.LNX.3.96.970914190806.674A-100000@purple.voicenet.com>"}], "subject": "Proxies", "file_year": 1997, "from": "\"Sam 'MaCpHReaK'  Chua\" <samchua@singnet.com.sg>", "raw_date": "Mon, 15 Sep 1997 06:16:37 +0800", "to": "cypherpunks@toad.com", "reply_to": null, "message_id": "<v03110701b04209789665@[165.21.186.199]>"}], "sender_id": "sam_macphreak_chua_samchua_at_singnet_com_sg_"}