{"count": 1, "from": "tomj@f111.n125.z1.FIDONET.ORG (tomj)", "threads": [{"message_hash": "6eea4498b31a569d07bb05e74752270fbe45ed1d52bf2ab4549bc000127eb7e6", "date": 720435619, "no_parent": null, "children": [], "subject": "PUBLIC_KEYS pre-Backbone topology", "file_year": 1992, "from": "tomj@f111.n125.z1.FIDONET.ORG (tomj)", "raw_date": "Fri, 30 Oct 92 02:00:19 PPE", "to": "cypherpunks@toad.com", "reply_to": null, "message_id": "<3383.2AF0F94F@fidogate.FIDONET.ORG>"}], "sender_id": "tomj_at_f111_n125_z1_fidonet_org_tomj_"}